{"2026-06-25":[{"nom":"O'HARA DU BOCAGE","naissance":"2024","date":"2026-06-25","hippodrome":"CAEN","lot":"","reduction":"","reduction_date":"","discipline":"Attelé","urlPerfs":"https://www.letrot.com/stats/chevaux/O%27HARA-DU-BOCAGE/ZmZbbAoHBQcQ/courses"},{"nom":"ODIN DE BUSSET","naissance":"2024","date":"2026-06-25","hippodrome":"CAEN","lot":"","reduction":"","reduction_date":"","discipline":"Attelé","urlPerfs":"https://www.letrot.com/stats/chevaux/ODIN-DE-BUSSET/ZmZbYgcGAQoV/courses"},{"nom":"OEUVRE ULTIME","naissance":"2024","date":"2026-06-25","hippodrome":"CAEN","lot":"","reduction":"","reduction_date":"","discipline":"Attelé","urlPerfs":"https://www.letrot.com/stats/chevaux/OEUVRE-ULTIME/ZmZbbQMABgIE/courses"},{"nom":"OLYMPE DE LA DUNE","naissance":"2024","date":"2026-06-25","hippodrome":"CAEN","lot":"","reduction":"","reduction_date":"","discipline":"Attelé","urlPerfs":"https://www.letrot.com/stats/chevaux/OLYMPE-DE-LA-DUNE/ZmZbYgsCBwcD/courses"},{"nom":"ONDINE DU GOUTIER","naissance":"2024","date":"2026-06-25","hippodrome":"CAEN","lot":"","reduction":"","reduction_date":"","discipline":"Attelé","urlPerfs":"https://www.letrot.com/stats/chevaux/ONDINE-DU-GOUTIER/ZmZbYQoIAQYD/courses"},{"nom":"OPOTO JIHAIME","naissance":"2024","date":"2026-06-25","hippodrome":"CAEN","lot":"","reduction":"","reduction_date":"","discipline":"Attelé","urlPerfs":"https://www.letrot.com/stats/chevaux/OPOTO-JIHAIME/ZmZbYgoGBwIW/courses"},{"nom":"OPUS MADRIK","naissance":"2024","date":"2026-06-25","hippodrome":"CAEN","lot":"","reduction":"","reduction_date":"","discipline":"Attelé","urlPerfs":"https://www.letrot.com/stats/chevaux/OPUS-MADRIK/ZmZbYgIGAQcF/courses"},{"nom":"OSCAR EFFE","naissance":"2024","date":"2026-06-25","hippodrome":"CAEN","lot":"","reduction":"","reduction_date":"","discipline":"Attelé","urlPerfs":"https://www.letrot.com/stats/chevaux/OSCAR-EFFE/ZmZbbAMGCwcO/courses"},{"nom":"OVADARA","naissance":"2024","date":"2026-06-25","hippodrome":"CAEN","lot":"","reduction":"","reduction_date":"","discipline":"Attelé","urlPerfs":"https://www.letrot.com/stats/chevaux/OVADARA/ZmZbbQEABgIF/courses"},{"nom":"OH MY CASTELLE","naissance":"2024","date":"2026-06-25","hippodrome":"CAEN","lot":"","reduction":"","reduction_date":"","discipline":"Attelé","urlPerfs":"https://www.letrot.com/stats/chevaux/OH-MY-CASTELLE/ZmZbYwEBCwse/courses"},{"nom":"OKOEUR DE BELLANDE","naissance":"2024","date":"2026-06-25","hippodrome":"CAEN","lot":"","reduction":"","reduction_date":"","discipline":"Attelé","urlPerfs":"https://www.letrot.com/stats/chevaux/OKOEUR-DE-BELLANDE/ZmZbbAMGAQoe/courses"},{"nom":"OLGA DAIRPET","naissance":"2024","date":"2026-06-25","hippodrome":"CAEN","lot":"","reduction":"","reduction_date":"","discipline":"Attelé","urlPerfs":"https://www.letrot.com/stats/chevaux/OLGA-DAIRPET/ZmZbbAQICwoG/courses"},{"nom":"OMAN D'ESCRIT","naissance":"2024","date":"2026-06-25","hippodrome":"CAEN","lot":"","reduction":"","reduction_date":"","discipline":"Attelé","urlPerfs":"https://www.letrot.com/stats/chevaux/OMAN-D%27ESCRIT/ZmZbYgQFBAIN/courses"},{"nom":"ONLY DU VIVIER","naissance":"2024","date":"2026-06-25","hippodrome":"CAEN","lot":"","reduction":"","reduction_date":"","discipline":"Attelé","urlPerfs":"https://www.letrot.com/stats/chevaux/ONLY-DU-VIVIER/ZmZbYQsACwEG/courses"},{"nom":"ONLY TIME ATOUT","naissance":"2024","date":"2026-06-25","hippodrome":"CAEN","lot":"","reduction":"","reduction_date":"","discipline":"Attelé","urlPerfs":"https://www.letrot.com/stats/chevaux/ONLY-TIME-ATOUT/ZmZbYwEJBQsY/courses"},{"nom":"OTONOMIE DU TRIO","naissance":"2024","date":"2026-06-25","hippodrome":"CAEN","lot":"","reduction":"","reduction_date":"","discipline":"Attelé","urlPerfs":"https://www.letrot.com/stats/chevaux/OTONOMIE-DU-TRIO/ZmZbbQQHBAsE/courses"},{"nom":"OUDZO DE REVE D'OR","naissance":"2024","date":"2026-06-25","hippodrome":"CAEN","lot":"","reduction":"","reduction_date":"","discipline":"Attelé","urlPerfs":"https://www.letrot.com/stats/chevaux/OUDZO-DE-REVE-D%27OR/ZmZbYgoBAwoR/courses"},{"nom":"OURAGANE DELA COUR","naissance":"2024","date":"2026-06-25","hippodrome":"CAEN","lot":"","reduction":"","reduction_date":"","discipline":"Attelé","urlPerfs":"https://www.letrot.com/stats/chevaux/OURAGANE-DELA-COUR/ZmZbbQsGAgQQ/courses"},{"nom":"OVNI DE CORDAY","naissance":"2024","date":"2026-06-25","hippodrome":"CAEN","lot":"","reduction":"","reduction_date":"","discipline":"Attelé","urlPerfs":"https://www.letrot.com/stats/chevaux/OVNI-DE-CORDAY/ZmZbbAYEAQsG/courses"},{"nom":"OAKS VALLEY","naissance":"2024","date":"2026-06-25","hippodrome":"CAEN","lot":"","reduction":"","reduction_date":"","discipline":"Attelé","urlPerfs":"https://www.letrot.com/stats/chevaux/OAKS-VALLEY/ZmZbYwEJAgEA/courses"},{"nom":"ODESSA ELLIS","naissance":"2024","date":"2026-06-25","hippodrome":"CAEN","lot":"","reduction":"","reduction_date":"","discipline":"Attelé","urlPerfs":"https://www.letrot.com/stats/chevaux/ODESSA-ELLIS/ZmZbYgIACwUV/courses"},{"nom":"OFFRE SPECIALE","naissance":"2024","date":"2026-06-25","hippodrome":"CAEN","lot":"","reduction":"","reduction_date":"","discipline":"Attelé","urlPerfs":"https://www.letrot.com/stats/chevaux/OFFRE-SPECIALE/ZmZbYwsDAwoS/courses"},{"nom":"OFFSHORE SOMOLLI","naissance":"2024","date":"2026-06-25","hippodrome":"CAEN","lot":"","reduction":"","reduction_date":"","discipline":"Attelé","urlPerfs":"https://www.letrot.com/stats/chevaux/OFFSHORE-SOMOLLI/ZmZbYQMEBQUB/courses"},{"nom":"OLASTAR ICEA","naissance":"2024","date":"2026-06-25","hippodrome":"CAEN","lot":"","reduction":"","reduction_date":"","discipline":"Attelé","urlPerfs":"https://www.letrot.com/stats/chevaux/OLASTAR-ICEA/ZmZbbAMFAQEV/courses"},{"nom":"OLYMPIC STAR","naissance":"2024","date":"2026-06-25","hippodrome":"CAEN","lot":"","reduction":"","reduction_date":"","discipline":"Attelé","urlPerfs":"https://www.letrot.com/stats/chevaux/OLYMPIC-STAR/ZmZbYwEHAQMS/courses"},{"nom":"OMYGA D'HELIOS","naissance":"2024","date":"2026-06-25","hippodrome":"CAEN","lot":"","reduction":"","reduction_date":"","discipline":"Attelé","urlPerfs":"https://www.letrot.com/stats/chevaux/OMYGA-D%27HELIOS/ZmZbYQQJAQsc/courses"},{"nom":"ORIOLA CITRUS","naissance":"2024","date":"2026-06-25","hippodrome":"CAEN","lot":"","reduction":"","reduction_date":"","discipline":"Attelé","urlPerfs":"https://www.letrot.com/stats/chevaux/ORIOLA-CITRUS/ZmZbYQUACwQf/courses"},{"nom":"OSCAR PIYA","naissance":"2024","date":"2026-06-25","hippodrome":"CAEN","lot":"","reduction":"","reduction_date":"","discipline":"Attelé","urlPerfs":"https://www.letrot.com/stats/chevaux/OSCAR-PIYA/ZmZbYwEBBQEZ/courses"},{"nom":"OURAGAN DE FAEL","naissance":"2024","date":"2026-06-25","hippodrome":"CAEN","lot":"","reduction":"","reduction_date":"","discipline":"Attelé","urlPerfs":"https://www.letrot.com/stats/chevaux/OURAGAN-DE-FAEL/ZmZbYgYIBwUW/courses"},{"nom":"OAKLAND","naissance":"2024","date":"2026-06-25","hippodrome":"CAEN","lot":"","reduction":"","reduction_date":"","discipline":"Attelé","urlPerfs":"https://www.letrot.com/stats/chevaux/OAKLAND/ZmZbYwAFCwMB/courses"},{"nom":"OCEANOS","naissance":"2024","date":"2026-06-25","hippodrome":"CAEN","lot":"","reduction":"","reduction_date":"","discipline":"Attelé","urlPerfs":"https://www.letrot.com/stats/chevaux/OCEANOS/ZmZbYgcABQEG/courses"},{"nom":"OFFICIELLE BOND","naissance":"2024","date":"2026-06-25","hippodrome":"CAEN","lot":"","reduction":"","reduction_date":"","discipline":"Attelé","urlPerfs":"https://www.letrot.com/stats/chevaux/OFFICIELLE-BOND/ZmZbYwsACgcY/courses"},{"nom":"OHANA DE REVE D'OR","naissance":"2024","date":"2026-06-25","hippodrome":"CAEN","lot":"","reduction":"","reduction_date":"","discipline":"Attelé","urlPerfs":"https://www.letrot.com/stats/chevaux/OHANA-DE-REVE-D%27OR/ZmZbYQUCBwAF/courses"},{"nom":"OLONNE CYNASOSO","naissance":"2024","date":"2026-06-25","hippodrome":"CAEN","lot":"","reduction":"","reduction_date":"","discipline":"Attelé","urlPerfs":"https://www.letrot.com/stats/chevaux/OLONNE-CYNASOSO/ZmZbYQoICwsX/courses"},{"nom":"OPIUM JIHAIME","naissance":"2024","date":"2026-06-25","hippodrome":"CAEN","lot":"","reduction":"","reduction_date":"","discipline":"Attelé","urlPerfs":"https://www.letrot.com/stats/chevaux/OPIUM-JIHAIME/ZmZbYgoGBwMX/courses"},{"nom":"ORIENTALE DANCE","naissance":"2024","date":"2026-06-25","hippodrome":"CAEN","lot":"","reduction":"","reduction_date":"","discipline":"Attelé","urlPerfs":"https://www.letrot.com/stats/chevaux/ORIENTALE-DANCE/ZmZbYwEACwEO/courses"},{"nom":"OSCAR DE TOURNAI","naissance":"2024","date":"2026-06-25","hippodrome":"CAEN","lot":"","reduction":"","reduction_date":"","discipline":"Attelé","urlPerfs":"https://www.letrot.com/stats/chevaux/OSCAR-DE-TOURNAI/ZmZbYwIDBQES/courses"},{"nom":"OSCAR DES BRUYERES","naissance":"2024","date":"2026-06-25","hippodrome":"CAEN","lot":"","reduction":"","reduction_date":"","discipline":"Attelé","urlPerfs":"https://www.letrot.com/stats/chevaux/OSCAR-DES-BRUYERES/ZmZbYwoDCgIV/courses"},{"nom":"OUVERT","naissance":"2024","date":"2026-06-25","hippodrome":"CAEN","lot":"","reduction":"","reduction_date":"","discipline":"Attelé","urlPerfs":"https://www.letrot.com/stats/chevaux/OUVERT/ZmZ9ZgIIBwUT/courses"},{"nom":"OCALA BEACH","naissance":"2024","date":"2026-06-25","hippodrome":"CAEN","lot":"","reduction":"","reduction_date":"","discipline":"Attelé","urlPerfs":"https://www.letrot.com/stats/chevaux/OCALA-BEACH/ZmZbYgQCBwUR/courses"},{"nom":"OFFRE IDEALE","naissance":"2024","date":"2026-06-25","hippodrome":"CAEN","lot":"","reduction":"","reduction_date":"","discipline":"Attelé","urlPerfs":"https://www.letrot.com/stats/chevaux/OFFRE-IDEALE/ZmZbYwsCCwAe/courses"},{"nom":"OFFSHORE MIJO","naissance":"2024","date":"2026-06-25","hippodrome":"CAEN","lot":"","reduction":"","reduction_date":"","discipline":"Attelé","urlPerfs":"https://www.letrot.com/stats/chevaux/OFFSHORE-MIJO/ZmZbYgYHCwQF/courses"},{"nom":"OH POUPOUILLE MIL","naissance":"2024","date":"2026-06-25","hippodrome":"CAEN","lot":"","reduction":"","reduction_date":"","discipline":"Attelé","urlPerfs":"https://www.letrot.com/stats/chevaux/OH-POUPOUILLE-MIL/ZmZbYwICBwQS/courses"},{"nom":"OLYMPE DU HOCQUET","naissance":"2024","date":"2026-06-25","hippodrome":"CAEN","lot":"","reduction":"","reduction_date":"","discipline":"Attelé","urlPerfs":"https://www.letrot.com/stats/chevaux/OLYMPE-DU-HOCQUET/ZmZbYgYJBwAD/courses"},{"nom":"OLYMPIA FLASH","naissance":"2024","date":"2026-06-25","hippodrome":"CAEN","lot":"","reduction":"","reduction_date":"","discipline":"Attelé","urlPerfs":"https://www.letrot.com/stats/chevaux/OLYMPIA-FLASH/ZmZbYgYFBgsY/courses"},{"nom":"OPALE D'ESPACE","naissance":"2024","date":"2026-06-25","hippodrome":"CAEN","lot":"","reduction":"","reduction_date":"","discipline":"Attelé","urlPerfs":"https://www.letrot.com/stats/chevaux/OPALE-D%27ESPACE/ZmZbYwIABAQZ/courses"},{"nom":"OPERADESMERVEILLES","naissance":"2024","date":"2026-06-25","hippodrome":"CAEN","lot":"","reduction":"","reduction_date":"","discipline":"Attelé","urlPerfs":"https://www.letrot.com/stats/chevaux/OPERADESMERVEILLES/ZmZbYwICBwMa/courses"},{"nom":"OPTIMISTA","naissance":"2024","date":"2026-06-25","hippodrome":"CAEN","lot":"","reduction":"","reduction_date":"","discipline":"Attelé","urlPerfs":"https://www.letrot.com/stats/chevaux/OPTIMISTA/ZmZbYwAFCgUO/courses"},{"nom":"ORCRUXE DU GARDEN","naissance":"2024","date":"2026-06-25","hippodrome":"CAEN","lot":"","reduction":"","reduction_date":"","discipline":"Attelé","urlPerfs":"https://www.letrot.com/stats/chevaux/ORCRUXE-DU-GARDEN/ZmZbbQQHAAsc/courses"},{"nom":"OPALE D'OR SAMAC","naissance":"2024","date":"2026-06-25","hippodrome":"CAEN","lot":"","reduction":"","reduction_date":"","discipline":"Attelé","urlPerfs":"https://www.letrot.com/stats/chevaux/OPALE-D%27OR-SAMAC/ZmZbYwEACgYT/courses"},{"nom":"ORCHESTRA ATALANTE","naissance":"2024","date":"2026-06-25","hippodrome":"CAEN","lot":"","reduction":"","reduction_date":"","discipline":"Attelé","urlPerfs":"https://www.letrot.com/stats/chevaux/ORCHESTRA-ATALANTE/ZmZbYgUGAQEe/courses"},{"nom":"OSTIE","naissance":"2024","date":"2026-06-25","hippodrome":"CAEN","lot":"","reduction":"","reduction_date":"","discipline":"Attelé","urlPerfs":"https://www.letrot.com/stats/chevaux/OSTIE/ZmZbYgsHCwEY/courses"},{"nom":"OTHELLO DE SIMM","naissance":"2024","date":"2026-06-25","hippodrome":"CAEN","lot":"","reduction":"","reduction_date":"","discipline":"Attelé","urlPerfs":"https://www.letrot.com/stats/chevaux/OTHELLO-DE-SIMM/ZmZbYQsDCgEW/courses"},{"nom":"OASIS SIXTY ONE","naissance":"2024","date":"2026-06-25","hippodrome":"CAEN","lot":"","reduction":"","reduction_date":"","discipline":"Attelé","urlPerfs":"https://www.letrot.com/stats/chevaux/OASIS-SIXTY-ONE/ZmZ9ZQsGAQUc/courses"},{"nom":"ODJY DU POMMEREUX","naissance":"2024","date":"2026-06-25","hippodrome":"CAEN","lot":"","reduction":"","reduction_date":"","discipline":"Attelé","urlPerfs":"https://www.letrot.com/stats/chevaux/ODJY-DU-POMMEREUX/ZmZbYgIGCgEa/courses"},{"nom":"OHIO LATIN","naissance":"2024","date":"2026-06-25","hippodrome":"CAEN","lot":"","reduction":"","reduction_date":"","discipline":"Attelé","urlPerfs":"https://www.letrot.com/stats/chevaux/OHIO-LATIN/ZmZbbAMHAgIG/courses"},{"nom":"OLTEN","naissance":"2024","date":"2026-06-25","hippodrome":"CAEN","lot":"","reduction":"","reduction_date":"","discipline":"Attelé","urlPerfs":"https://www.letrot.com/stats/chevaux/OLTEN/ZmZbYgQDAQcB/courses"},{"nom":"ONAHA STREET","naissance":"2024","date":"2026-06-25","hippodrome":"CAEN","lot":"","reduction":"","reduction_date":"","discipline":"Attelé","urlPerfs":"https://www.letrot.com/stats/chevaux/ONAHA-STREET/ZmZbYwMJBAMR/courses"},{"nom":"ONESHOT SOMOLLI","naissance":"2024","date":"2026-06-25","hippodrome":"CAEN","lot":"","reduction":"","reduction_date":"","discipline":"Attelé","urlPerfs":"https://www.letrot.com/stats/chevaux/ONESHOT-SOMOLLI/ZmZbYQUIAgUE/courses"},{"nom":"ORPHEA DU COJEUL","naissance":"2024","date":"2026-06-25","hippodrome":"CAEN","lot":"","reduction":"","reduction_date":"","discipline":"Attelé","urlPerfs":"https://www.letrot.com/stats/chevaux/ORPHEA-DU-COJEUL/ZmZbbQIFBwED/courses"},{"nom":"OULAN MAJOR","naissance":"2024","date":"2026-06-25","hippodrome":"CAEN","lot":"","reduction":"","reduction_date":"","discipline":"Attelé","urlPerfs":"https://www.letrot.com/stats/chevaux/OULAN-MAJOR/ZmZbYgYIAAIE/courses"},{"nom":"OWEN MIJACK","naissance":"2024","date":"2026-06-25","hippodrome":"CAEN","lot":"","reduction":"","reduction_date":"","discipline":"Attelé","urlPerfs":"https://www.letrot.com/stats/chevaux/OWEN-MIJACK/ZmZbYgQIAgsR/courses"},{"nom":"ODIN MARBEN","naissance":"2024","date":"2026-06-25","hippodrome":"CAEN","lot":"","reduction":"","reduction_date":"","discipline":"Attelé","urlPerfs":"https://www.letrot.com/stats/chevaux/ODIN-MARBEN/ZmZbYgoDCwYR/courses"},{"nom":"OH DESIREE","naissance":"2024","date":"2026-06-25","hippodrome":"CAEN","lot":"","reduction":"","reduction_date":"","discipline":"Attelé","urlPerfs":"https://www.letrot.com/stats/chevaux/OH-DESIREE/ZmZbYQoICwEe/courses"},{"nom":"OREGON FELD","naissance":"2024","date":"2026-06-25","hippodrome":"CAEN","lot":"","reduction":"","reduction_date":"","discipline":"Attelé","urlPerfs":"https://www.letrot.com/stats/chevaux/OREGON-FELD/ZmZbbAECBwYX/courses"},{"nom":"OTTAWA DE TILLARD","naissance":"2024","date":"2026-06-25","hippodrome":"CAEN","lot":"","reduction":"","reduction_date":"","discipline":"Attelé","urlPerfs":"https://www.letrot.com/stats/chevaux/OTTAWA-DE-TILLARD/ZmZbYQoIBQsO/courses"},{"nom":"OH LA STAR SAMAC","naissance":"2024","date":"2026-06-25","hippodrome":"CAEN","lot":"","reduction":"","reduction_date":"","discipline":"Attelé","urlPerfs":"https://www.letrot.com/stats/chevaux/OH-LA-STAR-SAMAC/ZmZbbAEBBQYE/courses"},{"nom":"ONE TIME BOURBON","naissance":"2024","date":"2026-06-25","hippodrome":"CAEN","lot":"","reduction":"","reduction_date":"","discipline":"Attelé","urlPerfs":"https://www.letrot.com/stats/chevaux/ONE-TIME-BOURBON/ZmZbYwEIBQQD/courses"},{"nom":"OUEST","naissance":"2024","date":"2026-06-25","hippodrome":"CAEN","lot":"","reduction":"","reduction_date":"","discipline":"Attelé","urlPerfs":"https://www.letrot.com/stats/chevaux/OUEST/ZmZbYgYJBQsA/courses"},{"nom":"OUTLANDING","naissance":"2024","date":"2026-06-25","hippodrome":"CAEN","lot":"","reduction":"","reduction_date":"","discipline":"Attelé","urlPerfs":"https://www.letrot.com/stats/chevaux/OUTLANDING/ZmZbYQoDAQAG/courses"},{"nom":"OVERDOSE FATALE","naissance":"2024","date":"2026-06-25","hippodrome":"CAEN","lot":"","reduction":"","reduction_date":"","discipline":"Attelé","urlPerfs":"https://www.letrot.com/stats/chevaux/OVERDOSE-FATALE/ZmZbYwECAgMT/courses"},{"nom":"OAKLAND GREEN","naissance":"2024","date":"2026-06-25","hippodrome":"CAEN","lot":"","reduction":"","reduction_date":"","discipline":"Attelé","urlPerfs":"https://www.letrot.com/stats/chevaux/OAKLAND-GREEN/ZmZbYgQGAwEH/courses"},{"nom":"OBERMAN D'OR","naissance":"2024","date":"2026-06-25","hippodrome":"CAEN","lot":"","reduction":"","reduction_date":"","discipline":"Attelé","urlPerfs":"https://www.letrot.com/stats/chevaux/OBERMAN-D%27OR/ZmZbYgYGBgAc/courses"},{"nom":"OLINA MIL","naissance":"2024","date":"2026-06-25","hippodrome":"CAEN","lot":"","reduction":"","reduction_date":"","discipline":"Attelé","urlPerfs":"https://www.letrot.com/stats/chevaux/OLINA-MIL/ZmZbYwEFBwoG/courses"},{"nom":"OLIVE","naissance":"2024","date":"2026-06-25","hippodrome":"CAEN","lot":"","reduction":"","reduction_date":"","discipline":"Attelé","urlPerfs":"https://www.letrot.com/stats/chevaux/OLIVE/ZmZbYwUEBwUS/courses"},{"nom":"OMAHA KERYANN","naissance":"2024","date":"2026-06-25","hippodrome":"CAEN","lot":"10","reduction":"","reduction_date":"","discipline":"Attelé","urlPerfs":"https://www.letrot.com/stats/chevaux/OMAHA-KERYANN/ZmZbYgoAAQoG/courses"},{"nom":"OMAHA WIN","naissance":"2024","date":"2026-06-25","hippodrome":"CAEN","lot":"","reduction":"","reduction_date":"","discipline":"Attelé","urlPerfs":"https://www.letrot.com/stats/chevaux/OMAHA-WIN/ZmZbYwYIAQMf/courses"},{"nom":"ONYX DE LA CHAULE","naissance":"2024","date":"2026-06-25","hippodrome":"CAEN","lot":"10","reduction":"","reduction_date":"","discipline":"Attelé","urlPerfs":"https://www.letrot.com/stats/chevaux/ONYX-DE-LA-CHAULE/ZmZbYwMGBAMS/courses"},{"nom":"ORATOR","naissance":"2024","date":"2026-06-25","hippodrome":"CAEN","lot":"","reduction":"","reduction_date":"","discipline":"Attelé","urlPerfs":"https://www.letrot.com/stats/chevaux/ORATOR/ZmZbbAoABwEa/courses"},{"nom":"OSITA D'URVILLE","naissance":"2024","date":"2026-06-25","hippodrome":"CAEN","lot":"","reduction":"","reduction_date":"","discipline":"Attelé","urlPerfs":"https://www.letrot.com/stats/chevaux/OSITA-D%27URVILLE/ZmZ9ZAAIAgAR/courses"},{"nom":"OSS DE L'ORMERIE","naissance":"2024","date":"2026-06-25","hippodrome":"CAEN","lot":"","reduction":"","reduction_date":"","discipline":"Attelé","urlPerfs":"https://www.letrot.com/stats/chevaux/OSS-DE-L%27ORMERIE/ZmZbYgQAAwUF/courses"},{"nom":"OH CHATELIER","naissance":"2024","date":"2026-06-25","hippodrome":"CAEN","lot":"11","reduction":"","reduction_date":"","discipline":"Attelé","urlPerfs":"https://www.letrot.com/stats/chevaux/OH-CHATELIER/ZmZbYwoAAwYN/courses"},{"nom":"OPTIMISTIC TWO","naissance":"2024","date":"2026-06-25","hippodrome":"CAEN","lot":"11","reduction":"","reduction_date":"","discipline":"Attelé","urlPerfs":"https://www.letrot.com/stats/chevaux/OPTIMISTIC-TWO/ZmZbYQUJBwIT/courses"},{"nom":"ORELIE ERA","naissance":"2024","date":"2026-06-25","hippodrome":"CAEN","lot":"","reduction":"","reduction_date":"","discipline":"Attelé","urlPerfs":"https://www.letrot.com/stats/chevaux/ORELIE-ERA/ZmZbYQMEBwIM/courses"},{"nom":"OUZO DU POMMEREUX","naissance":"2024","date":"2026-06-25","hippodrome":"CAEN","lot":"","reduction":"","reduction_date":"","discipline":"Attelé","urlPerfs":"https://www.letrot.com/stats/chevaux/OUZO-DU-POMMEREUX/ZmZbYwUIAAMf/courses"},{"nom":"OBASTI","naissance":"2024","date":"2026-06-25","hippodrome":"CAEN","lot":"12","reduction":"","reduction_date":"","discipline":"Attelé","urlPerfs":"https://www.letrot.com/stats/chevaux/OBASTI/ZmZbYgoCCwYa/courses"},{"nom":"OLVALAK STARCUT","naissance":"2024","date":"2026-06-25","hippodrome":"CAEN","lot":"12","reduction":"","reduction_date":"","discipline":"Attelé","urlPerfs":"https://www.letrot.com/stats/chevaux/OLVALAK-STARCUT/ZmZbYgoDAgQV/courses"},{"nom":"OLYMPE","naissance":"2024","date":"2026-06-25","hippodrome":"CAEN","lot":"","reduction":"","reduction_date":"","discipline":"Attelé","urlPerfs":"https://www.letrot.com/stats/chevaux/OLYMPE/ZmZbYgoACgQE/courses"},{"nom":"OLYMPE JOMUNA","naissance":"2024","date":"2026-06-25","hippodrome":"CAEN","lot":"12","reduction":"","reduction_date":"","discipline":"Attelé","urlPerfs":"https://www.letrot.com/stats/chevaux/OLYMPE-JOMUNA/ZmZbYgoAAwsE/courses"},{"nom":"OLYMPIA DE NIMA","naissance":"2024","date":"2026-06-25","hippodrome":"CAEN","lot":"12","reduction":"","reduction_date":"","discipline":"Attelé","urlPerfs":"https://www.letrot.com/stats/chevaux/OLYMPIA-DE-NIMA/ZmZbbQIGBwcf/courses"},{"nom":"ONE LOVE STORY","naissance":"2024","date":"2026-06-25","hippodrome":"CAEN","lot":"12","reduction":"","reduction_date":"","discipline":"Attelé","urlPerfs":"https://www.letrot.com/stats/chevaux/ONE-LOVE-STORY/ZmZbbAUGBQQD/courses"},{"nom":"OPPORTUNITE JHEQ","naissance":"2024","date":"2026-06-25","hippodrome":"CAEN","lot":"12","reduction":"","reduction_date":"","discipline":"Attelé","urlPerfs":"https://www.letrot.com/stats/chevaux/OPPORTUNITE-JHEQ/ZmZbYgcACgQV/courses"},{"nom":"ORSY DE BASSIERE","naissance":"2024","date":"2026-06-25","hippodrome":"CAEN","lot":"12","reduction":"","reduction_date":"","discipline":"Attelé","urlPerfs":"https://www.letrot.com/stats/chevaux/ORSY-DE-BASSIERE/ZmZbYgIGBgIc/courses"},{"nom":"OSIRIS DE LARRE","naissance":"2024","date":"2026-06-25","hippodrome":"CAEN","lot":"12","reduction":"","reduction_date":"","discipline":"Attelé","urlPerfs":"https://www.letrot.com/stats/chevaux/OSIRIS-DE-LARRE/ZmZbYwUIBgAf/courses"},{"nom":"OURANOS GAIA","naissance":"2024","date":"2026-06-25","hippodrome":"CAEN","lot":"12","reduction":"","reduction_date":"","discipline":"Attelé","urlPerfs":"https://www.letrot.com/stats/chevaux/OURANOS-GAIA/ZmZbYQQJAQEE/courses"},{"nom":"OLIGARQUE DE GAGOU","naissance":"2024","date":"2026-06-25","hippodrome":"CAEN","lot":"13","reduction":"","reduction_date":"","discipline":"Attelé","urlPerfs":"https://www.letrot.com/stats/chevaux/OLIGARQUE-DE-GAGOU/ZmZbYgsDAQUT/courses"},{"nom":"OLYMPE BADREC","naissance":"2024","date":"2026-06-25","hippodrome":"CAEN","lot":"13","reduction":"","reduction_date":"","discipline":"Attelé","urlPerfs":"https://www.letrot.com/stats/chevaux/OLYMPE-BADREC/ZmZbbAoHBAoe/courses"},{"nom":"OLYMPE ETOILEE","naissance":"2024","date":"2026-06-25","hippodrome":"CAEN","lot":"","reduction":"","reduction_date":"","discipline":"Attelé","urlPerfs":"https://www.letrot.com/stats/chevaux/OLYMPE-ETOILEE/ZmZbYwsEBAYM/courses"},{"nom":"ONE NIGHT IN RIO","naissance":"2024","date":"2026-06-25","hippodrome":"CAEN","lot":"13","reduction":"","reduction_date":"","discipline":"Attelé","urlPerfs":"https://www.letrot.com/stats/chevaux/ONE-NIGHT-IN-RIO/ZmZbYQoABAMa/courses"},{"nom":"OPALE SUPREME","naissance":"2024","date":"2026-06-25","hippodrome":"CAEN","lot":"13","reduction":"","reduction_date":"","discipline":"Attelé","urlPerfs":"https://www.letrot.com/stats/chevaux/OPALE-SUPREME/ZmZbYQUBBQUO/courses"},{"nom":"OLYFIELD MIJO","naissance":"2024","date":"2026-06-25","hippodrome":"CAEN","lot":"14","reduction":"","reduction_date":"","discipline":"Attelé","urlPerfs":"https://www.letrot.com/stats/chevaux/OLYFIELD-MIJO/ZmZbYgsCCwUV/courses"},{"nom":"ORIGINE DE JOUDES","naissance":"2024","date":"2026-06-25","hippodrome":"CAEN","lot":"14","reduction":"","reduction_date":"","discipline":"Attelé","urlPerfs":"https://www.letrot.com/stats/chevaux/ORIGINE-DE-JOUDES/ZmZbYgcGAwoM/courses"},{"nom":"ORION DE MALAC","naissance":"2024","date":"2026-06-25","hippodrome":"CAEN","lot":"14","reduction":"","reduction_date":"","discipline":"Attelé","urlPerfs":"https://www.letrot.com/stats/chevaux/ORION-DE-MALAC/ZmZbYwICBwAf/courses"},{"nom":"OSORNO VEDAQUAIS","naissance":"2024","date":"2026-06-25","hippodrome":"CAEN","lot":"14","reduction":"","reduction_date":"","discipline":"Attelé","urlPerfs":"https://www.letrot.com/stats/chevaux/OSORNO-VEDAQUAIS/ZmZbYQoIBwMR/courses"},{"nom":"ODACE SOMOLLI","naissance":"2024","date":"2026-06-25","hippodrome":"CAEN","lot":"15","reduction":"","reduction_date":"","discipline":"Attelé","urlPerfs":"https://www.letrot.com/stats/chevaux/ODACE-SOMOLLI/ZmZbYQUCAAcM/courses"},{"nom":"ODOACRE TURGOT","naissance":"2024","date":"2026-06-25","hippodrome":"CAEN","lot":"","reduction":"","reduction_date":"","discipline":"Attelé","urlPerfs":"https://www.letrot.com/stats/chevaux/ODOACRE-TURGOT/ZmZbYgQFBwsW/courses"},{"nom":"OEDEME","naissance":"2024","date":"2026-06-25","hippodrome":"CAEN","lot":"15","reduction":"","reduction_date":"","discipline":"Attelé","urlPerfs":"https://www.letrot.com/stats/chevaux/OEDEME/ZmZbYQUEAQIM/courses"},{"nom":"OH HAPPY DAY","naissance":"2024","date":"2026-06-25","hippodrome":"CAEN","lot":"15","reduction":"","reduction_date":"","discipline":"Attelé","urlPerfs":"https://www.letrot.com/stats/chevaux/OH-HAPPY-DAY/ZmZbYwYIAAYF/courses"},{"nom":"OLGA PASS","naissance":"2024","date":"2026-06-25","hippodrome":"CAEN","lot":"15","reduction":"","reduction_date":"","discipline":"Attelé","urlPerfs":"https://www.letrot.com/stats/chevaux/OLGA-PASS/ZmZbbQoICgYa/courses"},{"nom":"ONOLULU","naissance":"2024","date":"2026-06-25","hippodrome":"CAEN","lot":"15","reduction":"","reduction_date":"","discipline":"Attelé","urlPerfs":"https://www.letrot.com/stats/chevaux/ONOLULU/ZmZbYQsABAYD/courses"},{"nom":"ORIGIN MADRIK","naissance":"2024","date":"2026-06-25","hippodrome":"CAEN","lot":"16","reduction":"","reduction_date":"","discipline":"Attelé","urlPerfs":"https://www.letrot.com/stats/chevaux/ORIGIN-MADRIK/ZmZbYgsEBQoW/courses"},{"nom":"ORLANDO MAGIC","naissance":"2024","date":"2026-06-25","hippodrome":"CAEN","lot":"16","reduction":"","reduction_date":"","discipline":"Attelé","urlPerfs":"https://www.letrot.com/stats/chevaux/ORLANDO-MAGIC/ZmZbYgoCCwIH/courses"},{"nom":"OSMOSE MADRIK","naissance":"2024","date":"2026-06-25","hippodrome":"CAEN","lot":"16","reduction":"","reduction_date":"","discipline":"Attelé","urlPerfs":"https://www.letrot.com/stats/chevaux/OSMOSE-MADRIK/ZmZbYgoBBAEc/courses"},{"nom":"OUMIAK DE FELLIERE","naissance":"2024","date":"2026-06-25","hippodrome":"CAEN","lot":"16","reduction":"","reduction_date":"","discipline":"Attelé","urlPerfs":"https://www.letrot.com/stats/chevaux/OUMIAK-DE-FELLIERE/ZmZbYQQIBAoc/courses"},{"nom":"OZONE TURGOT","naissance":"2024","date":"2026-06-25","hippodrome":"CAEN","lot":"16","reduction":"","reduction_date":"","discipline":"Attelé","urlPerfs":"https://www.letrot.com/stats/chevaux/OZONE-TURGOT/ZmZbYgQGAgcW/courses"},{"nom":"OLYFIELD","naissance":"2024","date":"2026-06-25","hippodrome":"CAEN","lot":"17","reduction":"","reduction_date":"","discipline":"Attelé","urlPerfs":"https://www.letrot.com/stats/chevaux/OLYFIELD/ZmZbYgoDAgYX/courses"},{"nom":"ONOLULU BAY","naissance":"2024","date":"2026-06-25","hippodrome":"CAEN","lot":"17","reduction":"","reduction_date":"","discipline":"Attelé","urlPerfs":"https://www.letrot.com/stats/chevaux/ONOLULU-BAY/ZmZbYwMJAwAS/courses"},{"nom":"OPHELIA MESLERIE","naissance":"2024","date":"2026-06-25","hippodrome":"CAEN","lot":"17","reduction":"","reduction_date":"","discipline":"Attelé","urlPerfs":"https://www.letrot.com/stats/chevaux/OPHELIA-MESLERIE/ZmZbYgoHAwUS/courses"},{"nom":"ORELADY LORRAINE","naissance":"2024","date":"2026-06-25","hippodrome":"CAEN","lot":"17","reduction":"","reduction_date":"","discipline":"Attelé","urlPerfs":"https://www.letrot.com/stats/chevaux/ORELADY-LORRAINE/ZmZbYgQABwAV/courses"},{"nom":"ORGELET","naissance":"2024","date":"2026-06-25","hippodrome":"CAEN","lot":"17","reduction":"","reduction_date":"","discipline":"Attelé","urlPerfs":"https://www.letrot.com/stats/chevaux/ORGELET/ZmZbbQIFAAMS/courses"},{"nom":"OVERLAND","naissance":"2024","date":"2026-06-25","hippodrome":"CAEN","lot":"17","reduction":"","reduction_date":"","discipline":"Attelé","urlPerfs":"https://www.letrot.com/stats/chevaux/OVERLAND/ZmZbYQoCBAsZ/courses"},{"nom":"OBSESSION NIGHT","naissance":"2024","date":"2026-06-25","hippodrome":"CAEN","lot":"","reduction":"","reduction_date":"","discipline":"Attelé","urlPerfs":"https://www.letrot.com/stats/chevaux/OBSESSION-NIGHT/ZmZbYwEIBgIf/courses"},{"nom":"OH PETRUS","naissance":"2024","date":"2026-06-25","hippodrome":"CAEN","lot":"18","reduction":"","reduction_date":"","discipline":"Attelé","urlPerfs":"https://www.letrot.com/stats/chevaux/OH-PETRUS/ZmZbYgQECgMY/courses"},{"nom":"OLOROSO","naissance":"2024","date":"2026-06-25","hippodrome":"CAEN","lot":"18","reduction":"","reduction_date":"","discipline":"Attelé","urlPerfs":"https://www.letrot.com/stats/chevaux/OLOROSO/ZmZbYgQBBQAB/courses"},{"nom":"ONLY YOU MADRIK","naissance":"2024","date":"2026-06-25","hippodrome":"CAEN","lot":"18","reduction":"","reduction_date":"","discipline":"Attelé","urlPerfs":"https://www.letrot.com/stats/chevaux/ONLY-YOU-MADRIK/ZmZbYQUJBwAR/courses"},{"nom":"ORACE DE REVE D'OR","naissance":"2024","date":"2026-06-25","hippodrome":"CAEN","lot":"18","reduction":"","reduction_date":"","discipline":"Attelé","urlPerfs":"https://www.letrot.com/stats/chevaux/ORACE-DE-REVE-D%27OR/ZmZbYgoDCwsW/courses"},{"nom":"ORION DU PONT","naissance":"2024","date":"2026-06-25","hippodrome":"CAEN","lot":"18","reduction":"","reduction_date":"","discipline":"Attelé","urlPerfs":"https://www.letrot.com/stats/chevaux/ORION-DU-PONT/ZmZbYQUCAgsE/courses"},{"nom":"OTIS HAIZE","naissance":"2024","date":"2026-06-25","hippodrome":"CAEN","lot":"18","reduction":"","reduction_date":"","discipline":"Attelé","urlPerfs":"https://www.letrot.com/stats/chevaux/OTIS-HAIZE/ZmZ9ZAYIBgsT/courses"},{"nom":"OAKLAND DU NOYER","naissance":"2024","date":"2026-06-25","hippodrome":"CAEN","lot":"-","reduction":"","reduction_date":"","discipline":"Attelé","urlPerfs":"https://www.letrot.com/stats/chevaux/OAKLAND-DU-NOYER/ZmZbYwECAQMO/courses"},{"nom":"OAKLAND FIVE","naissance":"2024","date":"2026-06-25","hippodrome":"CAEN","lot":"-","reduction":"","reduction_date":"","discipline":"Attelé","urlPerfs":"https://www.letrot.com/stats/chevaux/OAKLAND-FIVE/ZmZbbAEEAAYH/courses"},{"nom":"OASIS DE BAIS","naissance":"2024","date":"2026-06-25","hippodrome":"CAEN","lot":"-","reduction":"","reduction_date":"","discipline":"Attelé","urlPerfs":"https://www.letrot.com/stats/chevaux/OASIS-DE-BAIS/ZmZbYwUEAAof/courses"},{"nom":"OBBIO DAIRPET","naissance":"2024","date":"2026-06-25","hippodrome":"CAEN","lot":"-","reduction":"","reduction_date":"","discipline":"Attelé","urlPerfs":"https://www.letrot.com/stats/chevaux/OBBIO-DAIRPET/ZmZbYQUFBwse/courses"},{"nom":"OBELIX DU CHERISAY","naissance":"2024","date":"2026-06-25","hippodrome":"CAEN","lot":"-","reduction":"","reduction_date":"","discipline":"Attelé","urlPerfs":"https://www.letrot.com/stats/chevaux/OBELIX-DU-CHERISAY/ZmZbbQoHAAMH/courses"},{"nom":"OBI WAN JIEL","naissance":"2024","date":"2026-06-25","hippodrome":"CAEN","lot":"-","reduction":"1''2\"0","reduction_date":"24/06/2026","discipline":"Attelé","urlPerfs":"https://www.letrot.com/stats/chevaux/OBI-WAN-JIEL/ZmZbYgEFCwIW/courses"},{"nom":"OBIWAN DU NOYER","naissance":"2024","date":"2026-06-25","hippodrome":"CAEN","lot":"-","reduction":"","reduction_date":"","discipline":"Attelé","urlPerfs":"https://www.letrot.com/stats/chevaux/OBIWAN-DU-NOYER/ZmZbYgQGAAcR/courses"},{"nom":"OBIWAN UP STAR","naissance":"2024","date":"2026-06-25","hippodrome":"CAEN","lot":"-","reduction":"","reduction_date":"","discipline":"Attelé","urlPerfs":"https://www.letrot.com/stats/chevaux/OBIWAN-UP-STAR/ZmZbYgoJBgUS/courses"},{"nom":"OBJECTIF LUNE","naissance":"2024","date":"2026-06-25","hippodrome":"CAEN","lot":"-","reduction":"","reduction_date":"","discipline":"Attelé","urlPerfs":"https://www.letrot.com/stats/chevaux/OBJECTIF-LUNE/ZmZbbAYCCwIW/courses"},{"nom":"OBSESSION","naissance":"2024","date":"2026-06-25","hippodrome":"CAEN","lot":"-","reduction":"","reduction_date":"","discipline":"Attelé","urlPerfs":"https://www.letrot.com/stats/chevaux/OBSESSION/ZmZbYgoACwAc/courses"},{"nom":"OBSIDIENNE JIEL","naissance":"2024","date":"2026-06-25","hippodrome":"CAEN","lot":"-","reduction":"","reduction_date":"","discipline":"Attelé","urlPerfs":"https://www.letrot.com/stats/chevaux/OBSIDIENNE-JIEL/ZmZbYwMIBQsA/courses"},{"nom":"OCEANE DE FLEUR","naissance":"2024","date":"2026-06-25","hippodrome":"CAEN","lot":"-","reduction":"","reduction_date":"","discipline":"Attelé","urlPerfs":"https://www.letrot.com/stats/chevaux/OCEANE-DE-FLEUR/ZmZbYQUBAQcB/courses"},{"nom":"OCELOT GRIFF","naissance":"2024","date":"2026-06-25","hippodrome":"CAEN","lot":"-","reduction":"","reduction_date":"","discipline":"Attelé","urlPerfs":"https://www.letrot.com/stats/chevaux/OCELOT-GRIFF/ZmZbbAcDAAIT/courses"},{"nom":"OCTAVIO MESLOIS","naissance":"2024","date":"2026-06-25","hippodrome":"CAEN","lot":"-","reduction":"","reduction_date":"","discipline":"Attelé","urlPerfs":"https://www.letrot.com/stats/chevaux/OCTAVIO-MESLOIS/ZmZbYQoIAQAN/courses"},{"nom":"OCTOPUS TY","naissance":"2024","date":"2026-06-25","hippodrome":"CAEN","lot":"-","reduction":"1''1\"9","reduction_date":"19/06/2026","discipline":"Attelé","urlPerfs":"https://www.letrot.com/stats/chevaux/OCTOPUS-TY/ZmZbYQoCBwMT/courses"},{"nom":"ODE A L'AMOUR","naissance":"2024","date":"2026-06-25","hippodrome":"CAEN","lot":"-","reduction":"","reduction_date":"","discipline":"Attelé","urlPerfs":"https://www.letrot.com/stats/chevaux/ODE-A-L%27AMOUR/ZmZbYgoDAAAc/courses"},{"nom":"ODE DES CHARMES","naissance":"2024","date":"2026-06-25","hippodrome":"CAEN","lot":"-","reduction":"","reduction_date":"","discipline":"Attelé","urlPerfs":"https://www.letrot.com/stats/chevaux/ODE-DES-CHARMES/ZmZbYQUABwMY/courses"},{"nom":"ODEON JIEL","naissance":"2024","date":"2026-06-25","hippodrome":"CAEN","lot":"-","reduction":"","reduction_date":"","discipline":"Attelé","urlPerfs":"https://www.letrot.com/stats/chevaux/ODEON-JIEL/ZmZbYQAICgsf/courses"},{"nom":"ODETTE JYL","naissance":"2024","date":"2026-06-25","hippodrome":"CAEN","lot":"-","reduction":"","reduction_date":"","discipline":"Attelé","urlPerfs":"https://www.letrot.com/stats/chevaux/ODETTE-JYL/ZmZbYQMFBwcf/courses"},{"nom":"ODIEUX DES RACQUES","naissance":"2024","date":"2026-06-25","hippodrome":"CAEN","lot":"-","reduction":"","reduction_date":"","discipline":"Attelé","urlPerfs":"https://www.letrot.com/stats/chevaux/ODIEUX-DES-RACQUES/ZmZbYgcGAAQa/courses"},{"nom":"ODIN DES BROUETS","naissance":"2024","date":"2026-06-25","hippodrome":"CAEN","lot":"-","reduction":"","reduction_date":"","discipline":"Attelé","urlPerfs":"https://www.letrot.com/stats/chevaux/ODIN-DES-BROUETS/ZmZbbAEECgQV/courses"},{"nom":"ODISSEA","naissance":"2024","date":"2026-06-25","hippodrome":"CAEN","lot":"-","reduction":"","reduction_date":"","discipline":"Attelé","urlPerfs":"https://www.letrot.com/stats/chevaux/ODISSEA/ZmZbYgcECwYT/courses"},{"nom":"ODYSSEE BOIS MORIN","naissance":"2024","date":"2026-06-25","hippodrome":"CAEN","lot":"-","reduction":"","reduction_date":"","discipline":"Attelé","urlPerfs":"https://www.letrot.com/stats/chevaux/ODYSSEE-BOIS-MORIN/ZmZbYwsJBAoO/courses"},{"nom":"OEILLET DE L'AUNAY","naissance":"2024","date":"2026-06-25","hippodrome":"CAEN","lot":"-","reduction":"","reduction_date":"","discipline":"Attelé","urlPerfs":"https://www.letrot.com/stats/chevaux/OEILLET-DE-L%27AUNAY/ZmZbYQEAAAcZ/courses"},{"nom":"OEILLET DE LARRE","naissance":"2024","date":"2026-06-25","hippodrome":"CAEN","lot":"-","reduction":"","reduction_date":"","discipline":"Attelé","urlPerfs":"https://www.letrot.com/stats/chevaux/OEILLET-DE-LARRE/ZmZbYwsABQEO/courses"},{"nom":"OETOILE DIAM","naissance":"2024","date":"2026-06-25","hippodrome":"CAEN","lot":"-","reduction":"","reduction_date":"","discipline":"Attelé","urlPerfs":"https://www.letrot.com/stats/chevaux/OETOILE-DIAM/ZmZbbAADAgsT/courses"},{"nom":"OEUVRE CLASSIQUE","naissance":"2024","date":"2026-06-25","hippodrome":"CAEN","lot":"-","reduction":"","reduction_date":"","discipline":"Attelé","urlPerfs":"https://www.letrot.com/stats/chevaux/OEUVRE-CLASSIQUE/ZmZbYwAABQIe/courses"},{"nom":"OF AMERICA","naissance":"2024","date":"2026-06-25","hippodrome":"CAEN","lot":"-","reduction":"1''2\"0","reduction_date":"24/06/2026","discipline":"Attelé","urlPerfs":"https://www.letrot.com/stats/chevaux/OF-AMERICA/ZmZbYwMJBgoG/courses"},{"nom":"OFEELING MIL","naissance":"2024","date":"2026-06-25","hippodrome":"CAEN","lot":"-","reduction":"1''1\"9","reduction_date":"19/06/2026","discipline":"Attelé","urlPerfs":"https://www.letrot.com/stats/chevaux/OFEELING-MIL/ZmZbYgYFCgQA/courses"},{"nom":"OFFENSIVE MESLOISE","naissance":"2024","date":"2026-06-25","hippodrome":"CAEN","lot":"-","reduction":"1''1\"9","reduction_date":"19/06/2026","discipline":"Attelé","urlPerfs":"https://www.letrot.com/stats/chevaux/OFFENSIVE-MESLOISE/ZmZbYgsCBwoF/courses"},{"nom":"OFFSHORE MESLOIS","naissance":"2024","date":"2026-06-25","hippodrome":"CAEN","lot":"-","reduction":"","reduction_date":"","discipline":"Attelé","urlPerfs":"https://www.letrot.com/stats/chevaux/OFFSHORE-MESLOIS/ZmZbYgcFAgIV/courses"},{"nom":"OH BELLE HOOKER","naissance":"2024","date":"2026-06-25","hippodrome":"CAEN","lot":"-","reduction":"","reduction_date":"","discipline":"Attelé","urlPerfs":"https://www.letrot.com/stats/chevaux/OH-BELLE-HOOKER/ZmZbbAMGAQEG/courses"},{"nom":"OH CHRIST ELEVEN","naissance":"2024","date":"2026-06-25","hippodrome":"CAEN","lot":"-","reduction":"","reduction_date":"","discipline":"Attelé","urlPerfs":"https://www.letrot.com/stats/chevaux/OH-CHRIST-ELEVEN/ZmZbbAcDAwUZ/courses"},{"nom":"OH MY DARLING LOVE","naissance":"2024","date":"2026-06-25","hippodrome":"CAEN","lot":"-","reduction":"","reduction_date":"","discipline":"Attelé","urlPerfs":"https://www.letrot.com/stats/chevaux/OH-MY-DARLING-LOVE/ZmZbYgYGAQID/courses"},{"nom":"OH SAINT PERE","naissance":"2024","date":"2026-06-25","hippodrome":"CAEN","lot":"-","reduction":"","reduction_date":"","discipline":"Attelé","urlPerfs":"https://www.letrot.com/stats/chevaux/OH-SAINT-PERE/ZmZbYQoABwQG/courses"},{"nom":"OHANA JIEL","naissance":"2024","date":"2026-06-25","hippodrome":"CAEN","lot":"-","reduction":"","reduction_date":"","discipline":"Attelé","urlPerfs":"https://www.letrot.com/stats/chevaux/OHANA-JIEL/ZmZbYgsHCwMa/courses"},{"nom":"OHMOLUNGMA CUT","naissance":"2024","date":"2026-06-25","hippodrome":"CAEN","lot":"-","reduction":"","reduction_date":"","discipline":"Attelé","urlPerfs":"https://www.letrot.com/stats/chevaux/OHMOLUNGMA-CUT/ZmZbYQoABgIe/courses"},{"nom":"OKABELLA D'ATOUT","naissance":"2024","date":"2026-06-25","hippodrome":"CAEN","lot":"-","reduction":"","reduction_date":"","discipline":"Attelé","urlPerfs":"https://www.letrot.com/stats/chevaux/OKABELLA-D%27ATOUT/ZmZ9ZAcBBwQD/courses"},{"nom":"OKAPI DE ROCHE","naissance":"2024","date":"2026-06-25","hippodrome":"CAEN","lot":"-","reduction":"","reduction_date":"","discipline":"Attelé","urlPerfs":"https://www.letrot.com/stats/chevaux/OKAPI-DE-ROCHE/ZmZbbAoJBgAB/courses"},{"nom":"OKAPI LEBEL","naissance":"","date":"2026-06-25","hippodrome":"CAEN","lot":"-","reduction":"","reduction_date":"","discipline":"Attelé","urlPerfs":"https://www.letrot.com/stats/chevaux/OKAPI-LEBEL/ZmZbYgIBAQUT/courses"},{"nom":"OKEKARINA POINT","naissance":"2024","date":"2026-06-25","hippodrome":"CAEN","lot":"-","reduction":"","reduction_date":"","discipline":"Attelé","urlPerfs":"https://www.letrot.com/stats/chevaux/OKEKARINA-POINT/ZmZbYwEJAwcS/courses"},{"nom":"OKINAWA JIEL","naissance":"2024","date":"2026-06-25","hippodrome":"CAEN","lot":"-","reduction":"","reduction_date":"","discipline":"Attelé","urlPerfs":"https://www.letrot.com/stats/chevaux/OKINAWA-JIEL/ZmZbYgEGAAMB/courses"},{"nom":"OKINAWA VET","naissance":"2024","date":"2026-06-25","hippodrome":"CAEN","lot":"-","reduction":"1''1\"9","reduction_date":"24/06/2026","discipline":"Attelé","urlPerfs":"https://www.letrot.com/stats/chevaux/OKINAWA-VET/ZmZbYgsCBQsB/courses"},{"nom":"OKINO GRIFF","naissance":"2024","date":"2026-06-25","hippodrome":"CAEN","lot":"-","reduction":"","reduction_date":"","discipline":"Attelé","urlPerfs":"https://www.letrot.com/stats/chevaux/OKINO-GRIFF/ZmZbbAcDAAES/courses"},{"nom":"OKLAHOMA","naissance":"2024","date":"2026-06-25","hippodrome":"CAEN","lot":"-","reduction":"","reduction_date":"","discipline":"Attelé","urlPerfs":"https://www.letrot.com/stats/chevaux/OKLAHOMA/ZmZbYQoCCwsR/courses"},{"nom":"OKLAHOMA CITY","naissance":"2024","date":"2026-06-25","hippodrome":"CAEN","lot":"-","reduction":"","reduction_date":"","discipline":"Attelé","urlPerfs":"https://www.letrot.com/stats/chevaux/OKLAHOMA-CITY/ZmZbbQUAAgoX/courses"},{"nom":"OKTANT FEUILLIEN","naissance":"2024","date":"2026-06-25","hippodrome":"CAEN","lot":"-","reduction":"","reduction_date":"","discipline":"Attelé","urlPerfs":"https://www.letrot.com/stats/chevaux/OKTANT-FEUILLIEN/ZmZbYwAIBAYD/courses"},{"nom":"OKTAR","naissance":"2024","date":"2026-06-25","hippodrome":"CAEN","lot":"-","reduction":"","reduction_date":"","discipline":"Attelé","urlPerfs":"https://www.letrot.com/stats/chevaux/OKTAR/ZmZbYwUHBQUc/courses"},{"nom":"OLAF DE VANDEL","naissance":"2024","date":"2026-06-25","hippodrome":"CAEN","lot":"-","reduction":"","reduction_date":"","discipline":"Attelé","urlPerfs":"https://www.letrot.com/stats/chevaux/OLAF-DE-VANDEL/ZmZbYgQCBgEB/courses"},{"nom":"OLFA MESLOISE","naissance":"2024","date":"2026-06-25","hippodrome":"CAEN","lot":"-","reduction":"","reduction_date":"","discipline":"Attelé","urlPerfs":"https://www.letrot.com/stats/chevaux/OLFA-MESLOISE/ZmZbYgQCAgsT/courses"},{"nom":"OLFEN","naissance":"2024","date":"2026-06-25","hippodrome":"CAEN","lot":"-","reduction":"","reduction_date":"","discipline":"Attelé","urlPerfs":"https://www.letrot.com/stats/chevaux/OLFEN/ZmZbYQsABwQR/courses"},{"nom":"OLGA DU RIB","naissance":"2024","date":"2026-06-25","hippodrome":"CAEN","lot":"-","reduction":"1''2\"0","reduction_date":"09/06/2026","discipline":"Attelé","urlPerfs":"https://www.letrot.com/stats/chevaux/OLGA-DU-RIB/ZmZbYQEBBAIa/courses"},{"nom":"OLITE","naissance":"2024","date":"2026-06-25","hippodrome":"CAEN","lot":"-","reduction":"","reduction_date":"","discipline":"Attelé","urlPerfs":"https://www.letrot.com/stats/chevaux/OLITE/ZmZbYQQGBwEA/courses"},{"nom":"OLIVARI","naissance":"2024","date":"2026-06-25","hippodrome":"CAEN","lot":"-","reduction":"","reduction_date":"","discipline":"Attelé","urlPerfs":"https://www.letrot.com/stats/chevaux/OLIVARI/ZmZbYwoBAAMe/courses"},{"nom":"OLMEDO","naissance":"2024","date":"2026-06-25","hippodrome":"CAEN","lot":"-","reduction":"","reduction_date":"","discipline":"Attelé","urlPerfs":"https://www.letrot.com/stats/chevaux/OLMEDO/ZmZbYQoACwEQ/courses"},{"nom":"OLSEN DE BANVILLE","naissance":"2024","date":"2026-06-25","hippodrome":"CAEN","lot":"-","reduction":"","reduction_date":"","discipline":"Attelé","urlPerfs":"https://www.letrot.com/stats/chevaux/OLSEN-DE-BANVILLE/ZmZbYgcFCwMQ/courses"},{"nom":"OLYMPE DELO","naissance":"2024","date":"2026-06-25","hippodrome":"CAEN","lot":"-","reduction":"","reduction_date":"","discipline":"Attelé","urlPerfs":"https://www.letrot.com/stats/chevaux/OLYMPE-DELO/ZmZbYgoACgID/courses"},{"nom":"OLYMPE DES LANDES","naissance":"2024","date":"2026-06-25","hippodrome":"CAEN","lot":"-","reduction":"","reduction_date":"","discipline":"Attelé","urlPerfs":"https://www.letrot.com/stats/chevaux/OLYMPE-DES-LANDES/ZmZbbAcFCwcf/courses"},{"nom":"OLYMPE DU QUENNE","naissance":"2024","date":"2026-06-25","hippodrome":"CAEN","lot":"-","reduction":"","reduction_date":"","discipline":"Attelé","urlPerfs":"https://www.letrot.com/stats/chevaux/OLYMPE-DU-QUENNE/ZmZbYwMGBQsY/courses"},{"nom":"OLYMPE MAJOR","naissance":"2024","date":"2026-06-25","hippodrome":"CAEN","lot":"-","reduction":"","reduction_date":"","discipline":"Attelé","urlPerfs":"https://www.letrot.com/stats/chevaux/OLYMPE-MAJOR/ZmZbYgcGAwIS/courses"},{"nom":"OLYMPE MIL","naissance":"2024","date":"2026-06-25","hippodrome":"CAEN","lot":"-","reduction":"1''1\"9","reduction_date":"19/06/2026","discipline":"Attelé","urlPerfs":"https://www.letrot.com/stats/chevaux/OLYMPE-MIL/ZmZbYgUFCgIE/courses"},{"nom":"OLYMPIA D'OR","naissance":"2024","date":"2026-06-25","hippodrome":"CAEN","lot":"-","reduction":"","reduction_date":"","discipline":"Attelé","urlPerfs":"https://www.letrot.com/stats/chevaux/OLYMPIA-D%27OR/ZmZbYgAEBwYY/courses"},{"nom":"OLYMPIA JENILOU","naissance":"2024","date":"2026-06-25","hippodrome":"CAEN","lot":"-","reduction":"1''1\"9","reduction_date":"24/06/2026","discipline":"Attelé","urlPerfs":"https://www.letrot.com/stats/chevaux/OLYMPIA-JENILOU/ZmZbYQoIAAUS/courses"},{"nom":"OLYMPIC DREAM","naissance":"2024","date":"2026-06-25","hippodrome":"CAEN","lot":"-","reduction":"","reduction_date":"","discipline":"Attelé","urlPerfs":"https://www.letrot.com/stats/chevaux/OLYMPIC-DREAM/ZmZbYwYIBwsR/courses"},{"nom":"OLYMPIC FAKIR","naissance":"2024","date":"2026-06-25","hippodrome":"CAEN","lot":"-","reduction":"","reduction_date":"","discipline":"Attelé","urlPerfs":"https://www.letrot.com/stats/chevaux/OLYMPIC-FAKIR/ZmZ9ZgEIAwcG/courses"},{"nom":"OMAGNIFICO DREAM","naissance":"2024","date":"2026-06-25","hippodrome":"CAEN","lot":"-","reduction":"","reduction_date":"","discipline":"Attelé","urlPerfs":"https://www.letrot.com/stats/chevaux/OMAGNIFICO-DREAM/ZmZbbQAJCwYF/courses"},{"nom":"OMAHA ANGOT","naissance":"2024","date":"2026-06-25","hippodrome":"CAEN","lot":"-","reduction":"","reduction_date":"","discipline":"Attelé","urlPerfs":"https://www.letrot.com/stats/chevaux/OMAHA-ANGOT/ZmZbbAACAwAf/courses"},{"nom":"OMAN MESLOIS","naissance":"2024","date":"2026-06-25","hippodrome":"CAEN","lot":"-","reduction":"","reduction_date":"","discipline":"Attelé","urlPerfs":"https://www.letrot.com/stats/chevaux/OMAN-MESLOIS/ZmZbYwYGAgEc/courses"},{"nom":"OMBELINE JIEL","naissance":"2024","date":"2026-06-25","hippodrome":"CAEN","lot":"-","reduction":"","reduction_date":"","discipline":"Attelé","urlPerfs":"https://www.letrot.com/stats/chevaux/OMBELINE-JIEL/ZmZbbAADBwYS/courses"},{"nom":"OMEGA DU PONT","naissance":"2024","date":"2026-06-25","hippodrome":"CAEN","lot":"-","reduction":"","reduction_date":"","discipline":"Attelé","urlPerfs":"https://www.letrot.com/stats/chevaux/OMEGA-DU-PONT/ZmZbbAIBAAQX/courses"},{"nom":"OMERTA ERCA","naissance":"2024","date":"2026-06-25","hippodrome":"CAEN","lot":"-","reduction":"","reduction_date":"","discipline":"Attelé","urlPerfs":"https://www.letrot.com/stats/chevaux/OMERTA-ERCA/ZmZbYgQDAwYF/courses"},{"nom":"ON MY MIND","naissance":"2024","date":"2026-06-25","hippodrome":"CAEN","lot":"-","reduction":"","reduction_date":"","discipline":"Attelé","urlPerfs":"https://www.letrot.com/stats/chevaux/ON-MY-MIND/ZmZbbAEEAQUS/courses"},{"nom":"ON MY WAY JYL","naissance":"2024","date":"2026-06-25","hippodrome":"CAEN","lot":"-","reduction":"","reduction_date":"","discipline":"Attelé","urlPerfs":"https://www.letrot.com/stats/chevaux/ON-MY-WAY-JYL/ZmZbYQUABAUA/courses"},{"nom":"ONA DU RIB","naissance":"2024","date":"2026-06-25","hippodrome":"CAEN","lot":"-","reduction":"","reduction_date":"","discipline":"Attelé","urlPerfs":"https://www.letrot.com/stats/chevaux/ONA-DU-RIB/ZmZbYgYHBQEH/courses"},{"nom":"ONAMARIA","naissance":"2024","date":"2026-06-25","hippodrome":"CAEN","lot":"-","reduction":"","reduction_date":"","discipline":"Attelé","urlPerfs":"https://www.letrot.com/stats/chevaux/ONAMARIA/ZmZbYQoDAgQB/courses"},{"nom":"ONDANSE DU RIB","naissance":"2024","date":"2026-06-25","hippodrome":"CAEN","lot":"-","reduction":"","reduction_date":"","discipline":"Attelé","urlPerfs":"https://www.letrot.com/stats/chevaux/ONDANSE-DU-RIB/ZmZbbAQCCgcf/courses"},{"nom":"ONDINE JIEL","naissance":"2024","date":"2026-06-25","hippodrome":"CAEN","lot":"-","reduction":"","reduction_date":"","discipline":"Attelé","urlPerfs":"https://www.letrot.com/stats/chevaux/ONDINE-JIEL/ZmZbbAAJAQEQ/courses"},{"nom":"ONE BOY DES BORDES","naissance":"2024","date":"2026-06-25","hippodrome":"CAEN","lot":"-","reduction":"","reduction_date":"","discipline":"Attelé","urlPerfs":"https://www.letrot.com/stats/chevaux/ONE-BOY-DES-BORDES/ZmZbYwYJCwIf/courses"},{"nom":"ONE LIFE","naissance":"2024","date":"2026-06-25","hippodrome":"CAEN","lot":"-","reduction":"","reduction_date":"","discipline":"Attelé","urlPerfs":"https://www.letrot.com/stats/chevaux/ONE-LIFE/ZmZbYwMICwAX/courses"},{"nom":"ONE LOVE DU WALLON","naissance":"2024","date":"2026-06-25","hippodrome":"CAEN","lot":"-","reduction":"","reduction_date":"","discipline":"Attelé","urlPerfs":"https://www.letrot.com/stats/chevaux/ONE-LOVE-DU-WALLON/ZmZbbAEBBAAX/courses"},{"nom":"ONE MIL","naissance":"2024","date":"2026-06-25","hippodrome":"CAEN","lot":"-","reduction":"1''2\"0","reduction_date":"19/06/2026","discipline":"Attelé","urlPerfs":"https://www.letrot.com/stats/chevaux/ONE-MIL/ZmZbYgEECgQE/courses"},{"nom":"ONE MORE DELO","naissance":"2024","date":"2026-06-25","hippodrome":"CAEN","lot":"-","reduction":"","reduction_date":"","discipline":"Attelé","urlPerfs":"https://www.letrot.com/stats/chevaux/ONE-MORE-DELO/ZmZbYgQGBQIQ/courses"},{"nom":"ONE MORE LIFE","naissance":"2024","date":"2026-06-25","hippodrome":"CAEN","lot":"-","reduction":"","reduction_date":"","discipline":"Attelé","urlPerfs":"https://www.letrot.com/stats/chevaux/ONE-MORE-LIFE/ZmZbYQUJBAcH/courses"},{"nom":"ONE MORE TIME","naissance":"2024","date":"2026-06-25","hippodrome":"CAEN","lot":"-","reduction":"","reduction_date":"","discipline":"Attelé","urlPerfs":"https://www.letrot.com/stats/chevaux/ONE-MORE-TIME/ZmZbYwAFAQAT/courses"},{"nom":"ONE SIXTY ONE","naissance":"2024","date":"2026-06-25","hippodrome":"CAEN","lot":"-","reduction":"","reduction_date":"","discipline":"Attelé","urlPerfs":"https://www.letrot.com/stats/chevaux/ONE-SIXTY-ONE/ZmZbYQoIBAYa/courses"},{"nom":"ONINA MIKA","naissance":"2024","date":"2026-06-25","hippodrome":"CAEN","lot":"-","reduction":"","reduction_date":"","discipline":"Attelé","urlPerfs":"https://www.letrot.com/stats/chevaux/ONINA-MIKA/ZmZbbAIBBQEQ/courses"},{"nom":"ONIRIQUE","naissance":"2024","date":"2026-06-25","hippodrome":"CAEN","lot":"-","reduction":"1''1\"7","reduction_date":"24/06/2026","discipline":"Attelé","urlPerfs":"https://www.letrot.com/stats/chevaux/ONIRIQUE/ZmZbYgoBAwEZ/courses"},{"nom":"ONLY ETRE","naissance":"2024","date":"2026-06-25","hippodrome":"CAEN","lot":"-","reduction":"","reduction_date":"","discipline":"Attelé","urlPerfs":"https://www.letrot.com/stats/chevaux/ONLY-ETRE/ZmZbYgEGAgYY/courses"},{"nom":"ONTARIO SEA","naissance":"2024","date":"2026-06-25","hippodrome":"CAEN","lot":"-","reduction":"","reduction_date":"","discipline":"Attelé","urlPerfs":"https://www.letrot.com/stats/chevaux/ONTARIO-SEA/ZmZbYgYJBAIZ/courses"},{"nom":"OPALE DE LA COTE","naissance":"2024","date":"2026-06-25","hippodrome":"CAEN","lot":"-","reduction":"","reduction_date":"","discipline":"Attelé","urlPerfs":"https://www.letrot.com/stats/chevaux/OPALE-DE-LA-COTE/ZmZbYwIJCwET/courses"},{"nom":"OPALE GLYCINES","naissance":"2024","date":"2026-06-25","hippodrome":"CAEN","lot":"-","reduction":"","reduction_date":"","discipline":"Attelé","urlPerfs":"https://www.letrot.com/stats/chevaux/OPALE-GLYCINES/ZmZbYwcAAwME/courses"},{"nom":"OPALINE JIEL","naissance":"2024","date":"2026-06-25","hippodrome":"CAEN","lot":"-","reduction":"","reduction_date":"","discipline":"Attelé","urlPerfs":"https://www.letrot.com/stats/chevaux/OPALINE-JIEL/ZmZ9ZQoFBgQG/courses"},{"nom":"OPALIO","naissance":"2024","date":"2026-06-25","hippodrome":"CAEN","lot":"-","reduction":"","reduction_date":"","discipline":"Attelé","urlPerfs":"https://www.letrot.com/stats/chevaux/OPALIO/ZmZbYQAJAgEB/courses"},{"nom":"OPEN SIXTY ONE","naissance":"2024","date":"2026-06-25","hippodrome":"CAEN","lot":"-","reduction":"","reduction_date":"","discipline":"Attelé","urlPerfs":"https://www.letrot.com/stats/chevaux/OPEN-SIXTY-ONE/ZmZbbQYECgsH/courses"},{"nom":"OPEN THE ROAD","naissance":"2024","date":"2026-06-25","hippodrome":"CAEN","lot":"-","reduction":"","reduction_date":"","discipline":"Attelé","urlPerfs":"https://www.letrot.com/stats/chevaux/OPEN-THE-ROAD/ZmZbYwsDAAMR/courses"},{"nom":"OPERA DE PARIS","naissance":"2024","date":"2026-06-25","hippodrome":"CAEN","lot":"-","reduction":"","reduction_date":"","discipline":"Attelé","urlPerfs":"https://www.letrot.com/stats/chevaux/OPERA-DE-PARIS/ZmZbbQoICwES/courses"},{"nom":"OPERA DU CAIEU","naissance":"2024","date":"2026-06-25","hippodrome":"CAEN","lot":"-","reduction":"","reduction_date":"","discipline":"Attelé","urlPerfs":"https://www.letrot.com/stats/chevaux/OPERA-DU-CAIEU/ZmZbYwcECwUY/courses"},{"nom":"OPERA DU DOLLAR","naissance":"2024","date":"2026-06-25","hippodrome":"CAEN","lot":"-","reduction":"","reduction_date":"","discipline":"Attelé","urlPerfs":"https://www.letrot.com/stats/chevaux/OPERA-DU-DOLLAR/ZmZbYQAJAgsa/courses"},{"nom":"OPERA PIYA","naissance":"2024","date":"2026-06-25","hippodrome":"CAEN","lot":"-","reduction":"","reduction_date":"","discipline":"Attelé","urlPerfs":"https://www.letrot.com/stats/chevaux/OPERA-PIYA/ZmZbYgoDCwUQ/courses"},{"nom":"OPGUN ICEA","naissance":"2024","date":"2026-06-25","hippodrome":"CAEN","lot":"-","reduction":"","reduction_date":"","discipline":"Attelé","urlPerfs":"https://www.letrot.com/stats/chevaux/OPGUN-ICEA/ZmZbYgYGAQcH/courses"},{"nom":"OPIO ANGELE","naissance":"2024","date":"2026-06-25","hippodrome":"CAEN","lot":"-","reduction":"","reduction_date":"","discipline":"Attelé","urlPerfs":"https://www.letrot.com/stats/chevaux/OPIO-ANGELE/ZmZbYwMGCwMN/courses"},{"nom":"OPIUM DRY","naissance":"2024","date":"2026-06-25","hippodrome":"CAEN","lot":"-","reduction":"","reduction_date":"","discipline":"Attelé","urlPerfs":"https://www.letrot.com/stats/chevaux/OPIUM-DRY/ZmZbYgQDBQIR/courses"},{"nom":"OPIUM MESLOIS","naissance":"2024","date":"2026-06-25","hippodrome":"CAEN","lot":"-","reduction":"","reduction_date":"","discipline":"Attelé","urlPerfs":"https://www.letrot.com/stats/chevaux/OPIUM-MESLOIS/ZmZbYgQCAgIE/courses"},{"nom":"OPTIMUS DELKARLITO","naissance":"2024","date":"2026-06-25","hippodrome":"CAEN","lot":"-","reduction":"","reduction_date":"","discipline":"Attelé","urlPerfs":"https://www.letrot.com/stats/chevaux/OPTIMUS-DELKARLITO/ZmZbYgYFBQQR/courses"},{"nom":"OPTIMUS MESLOIS","naissance":"2024","date":"2026-06-25","hippodrome":"CAEN","lot":"-","reduction":"1''1\"9","reduction_date":"19/06/2026","discipline":"Attelé","urlPerfs":"https://www.letrot.com/stats/chevaux/OPTIMUS-MESLOIS/ZmZbYwAFCwUa/courses"},{"nom":"OPUS MESLOIS","naissance":"2024","date":"2026-06-25","hippodrome":"CAEN","lot":"-","reduction":"1''1\"9","reduction_date":"19/06/2026","discipline":"Attelé","urlPerfs":"https://www.letrot.com/stats/chevaux/OPUS-MESLOIS/ZmZbYgcACgMc/courses"},{"nom":"OR PRECIEUX","naissance":"2024","date":"2026-06-25","hippodrome":"CAEN","lot":"-","reduction":"","reduction_date":"","discipline":"Attelé","urlPerfs":"https://www.letrot.com/stats/chevaux/OR-PRECIEUX/ZmZbYgsIAgYM/courses"},{"nom":"ORACE SERVINOIS","naissance":"2024","date":"2026-06-25","hippodrome":"CAEN","lot":"-","reduction":"","reduction_date":"","discipline":"Attelé","urlPerfs":"https://www.letrot.com/stats/chevaux/ORACE-SERVINOIS/ZmZ9ZgYDCwsT/courses"},{"nom":"ORACIO LIO","naissance":"2024","date":"2026-06-25","hippodrome":"CAEN","lot":"-","reduction":"","reduction_date":"","discipline":"Attelé","urlPerfs":"https://www.letrot.com/stats/chevaux/ORACIO-LIO/ZmZbYgQIBQQR/courses"},{"nom":"ORAGE BENOIT","naissance":"2024","date":"2026-06-25","hippodrome":"CAEN","lot":"-","reduction":"","reduction_date":"","discipline":"Attelé","urlPerfs":"https://www.letrot.com/stats/chevaux/ORAGE-BENOIT/ZmZbYQsEAwYF/courses"},{"nom":"ORAGEUSE","naissance":"2024","date":"2026-06-25","hippodrome":"CAEN","lot":"-","reduction":"","reduction_date":"","discipline":"Attelé","urlPerfs":"https://www.letrot.com/stats/chevaux/ORAGEUSE/ZmZbYwUFAAUR/courses"},{"nom":"ORANGER DU RIB","naissance":"2024","date":"2026-06-25","hippodrome":"CAEN","lot":"-","reduction":"","reduction_date":"","discipline":"Attelé","urlPerfs":"https://www.letrot.com/stats/chevaux/ORANGER-DU-RIB/ZmZbYgYJAgUM/courses"},{"nom":"ORCHIDEE DU RIB","naissance":"2024","date":"2026-06-25","hippodrome":"CAEN","lot":"-","reduction":"","reduction_date":"","discipline":"Attelé","urlPerfs":"https://www.letrot.com/stats/chevaux/ORCHIDEE-DU-RIB/ZmZbYQUBAgMT/courses"},{"nom":"OREADE DU YUCCA","naissance":"2024","date":"2026-06-25","hippodrome":"CAEN","lot":"-","reduction":"","reduction_date":"","discipline":"Attelé","urlPerfs":"https://www.letrot.com/stats/chevaux/OREADE-DU-YUCCA/ZmZbYwMJBgAN/courses"},{"nom":"OREGON DE PLAY","naissance":"2024","date":"2026-06-25","hippodrome":"CAEN","lot":"-","reduction":"","reduction_date":"","discipline":"Attelé","urlPerfs":"https://www.letrot.com/stats/chevaux/OREGON-DE-PLAY/ZmZbYwQBAAES/courses"},{"nom":"ORELIE FLORE","naissance":"2024","date":"2026-06-25","hippodrome":"CAEN","lot":"-","reduction":"","reduction_date":"","discipline":"Attelé","urlPerfs":"https://www.letrot.com/stats/chevaux/ORELIE-FLORE/ZmZbYQUCBwcE/courses"},{"nom":"ORELINDA","naissance":"2024","date":"2026-06-25","hippodrome":"CAEN","lot":"-","reduction":"","reduction_date":"","discipline":"Attelé","urlPerfs":"https://www.letrot.com/stats/chevaux/ORELINDA/ZmZbbQQIBQoA/courses"},{"nom":"ORFEE DU QUENNE","naissance":"2024","date":"2026-06-25","hippodrome":"CAEN","lot":"-","reduction":"","reduction_date":"","discipline":"Attelé","urlPerfs":"https://www.letrot.com/stats/chevaux/ORFEE-DU-QUENNE/ZmZbYgQHCwIN/courses"},{"nom":"ORIA DU RIB","naissance":"2024","date":"2026-06-25","hippodrome":"CAEN","lot":"-","reduction":"1''1\"9","reduction_date":"09/06/2026","discipline":"Attelé","urlPerfs":"https://www.letrot.com/stats/chevaux/ORIA-DU-RIB/ZmZbbAoGCgcW/courses"},{"nom":"ORIANNA JIEL","naissance":"2024","date":"2026-06-25","hippodrome":"CAEN","lot":"-","reduction":"","reduction_date":"","discipline":"Attelé","urlPerfs":"https://www.letrot.com/stats/chevaux/ORIANNA-JIEL/ZmZbYgEGAgIF/courses"},{"nom":"ORIELLA DU NOYER","naissance":"2024","date":"2026-06-25","hippodrome":"CAEN","lot":"-","reduction":"","reduction_date":"","discipline":"Attelé","urlPerfs":"https://www.letrot.com/stats/chevaux/ORIELLA-DU-NOYER/ZmZbbAcDBAME/courses"},{"nom":"ORIGINAL ARTIST","naissance":"2024","date":"2026-06-25","hippodrome":"CAEN","lot":"-","reduction":"","reduction_date":"","discipline":"Attelé","urlPerfs":"https://www.letrot.com/stats/chevaux/ORIGINAL-ARTIST/ZmZbYwYIAQAT/courses"},{"nom":"ORIGINAL MAN","naissance":"2024","date":"2026-06-25","hippodrome":"CAEN","lot":"-","reduction":"","reduction_date":"","discipline":"Attelé","urlPerfs":"https://www.letrot.com/stats/chevaux/ORIGINAL-MAN/ZmZbYwAABQUQ/courses"},{"nom":"ORIGNY","naissance":"2024","date":"2026-06-25","hippodrome":"CAEN","lot":"-","reduction":"","reduction_date":"","discipline":"Attelé","urlPerfs":"https://www.letrot.com/stats/chevaux/ORIGNY/ZmZbYQAJBwAE/courses"},{"nom":"ORIOLE DU RIB","naissance":"2024","date":"2026-06-25","hippodrome":"CAEN","lot":"-","reduction":"1''1\"9","reduction_date":"09/06/2026","discipline":"Attelé","urlPerfs":"https://www.letrot.com/stats/chevaux/ORIOLE-DU-RIB/ZmZbbAQEAgoO/courses"},{"nom":"ORION D'ESPACE","naissance":"2024","date":"2026-06-25","hippodrome":"CAEN","lot":"-","reduction":"","reduction_date":"","discipline":"Attelé","urlPerfs":"https://www.letrot.com/stats/chevaux/ORION-D%27ESPACE/ZmZbYgoHAQEa/courses"},{"nom":"ORION DE SOMMAIRE","naissance":"2024","date":"2026-06-25","hippodrome":"CAEN","lot":"-","reduction":"","reduction_date":"","discipline":"Attelé","urlPerfs":"https://www.letrot.com/stats/chevaux/ORION-DE-SOMMAIRE/ZmZbbQQHBgYE/courses"},{"nom":"ORION DREAM","naissance":"2024","date":"2026-06-25","hippodrome":"CAEN","lot":"-","reduction":"","reduction_date":"","discipline":"Attelé","urlPerfs":"https://www.letrot.com/stats/chevaux/ORION-DREAM/ZmZbYgoAAwoa/courses"},{"nom":"ORION VAROIS","naissance":"2024","date":"2026-06-25","hippodrome":"CAEN","lot":"-","reduction":"","reduction_date":"","discipline":"Attelé","urlPerfs":"https://www.letrot.com/stats/chevaux/ORION-VAROIS/ZmZbYgQHAwAc/courses"},{"nom":"ORION VENESI","naissance":"2024","date":"2026-06-25","hippodrome":"CAEN","lot":"-","reduction":"","reduction_date":"","discipline":"Attelé","urlPerfs":"https://www.letrot.com/stats/chevaux/ORION-VENESI/ZmZ9ZQsFAAQW/courses"},{"nom":"ORIZABA","naissance":"2024","date":"2026-06-25","hippodrome":"CAEN","lot":"-","reduction":"","reduction_date":"","discipline":"Attelé","urlPerfs":"https://www.letrot.com/stats/chevaux/ORIZABA/ZmZbbAAGAAMH/courses"},{"nom":"ORLANDO D'AUVRECY","naissance":"2024","date":"2026-06-25","hippodrome":"CAEN","lot":"-","reduction":"","reduction_date":"","discipline":"Attelé","urlPerfs":"https://www.letrot.com/stats/chevaux/ORLANDO-D%27AUVRECY/ZmZbYQEBBAUc/courses"},{"nom":"ORLANDO DIGEO","naissance":"2024","date":"2026-06-25","hippodrome":"CAEN","lot":"-","reduction":"","reduction_date":"","discipline":"Attelé","urlPerfs":"https://www.letrot.com/stats/chevaux/ORLANDO-DIGEO/ZmZbYQsIAwAc/courses"},{"nom":"ORLANDO DU CAIEU","naissance":"2024","date":"2026-06-25","hippodrome":"CAEN","lot":"-","reduction":"","reduction_date":"","discipline":"Attelé","urlPerfs":"https://www.letrot.com/stats/chevaux/ORLANDO-DU-CAIEU/ZmZbbAUGBQIX/courses"},{"nom":"ORLANDO FURIOSO","naissance":"2024","date":"2026-06-25","hippodrome":"CAEN","lot":"-","reduction":"","reduction_date":"","discipline":"Attelé","urlPerfs":"https://www.letrot.com/stats/chevaux/ORLANDO-FURIOSO/ZmZbYQoDAAAX/courses"},{"nom":"ORNAISE DU HANOY","naissance":"2024","date":"2026-06-25","hippodrome":"CAEN","lot":"-","reduction":"","reduction_date":"","discipline":"Attelé","urlPerfs":"https://www.letrot.com/stats/chevaux/ORNAISE-DU-HANOY/ZmZ9ZAoFAAAZ/courses"},{"nom":"ORNITERA","naissance":"2024","date":"2026-06-25","hippodrome":"CAEN","lot":"-","reduction":"","reduction_date":"","discipline":"Attelé","urlPerfs":"https://www.letrot.com/stats/chevaux/ORNITERA/ZmZbbAIEBwEO/courses"},{"nom":"ORO VERO","naissance":"2024","date":"2026-06-25","hippodrome":"CAEN","lot":"-","reduction":"","reduction_date":"","discipline":"Attelé","urlPerfs":"https://www.letrot.com/stats/chevaux/ORO-VERO/ZmZbYgQDAQEM/courses"},{"nom":"ORPAILLEUR PECE","naissance":"2024","date":"2026-06-25","hippodrome":"CAEN","lot":"-","reduction":"","reduction_date":"","discipline":"Attelé","urlPerfs":"https://www.letrot.com/stats/chevaux/ORPAILLEUR-PECE/ZmZbYwICBQIF/courses"},{"nom":"ORPHEE DES CHARMES","naissance":"2024","date":"2026-06-25","hippodrome":"CAEN","lot":"-","reduction":"","reduction_date":"","discipline":"Attelé","urlPerfs":"https://www.letrot.com/stats/chevaux/ORPHEE-DES-CHARMES/ZmZbYQoDCgIE/courses"},{"nom":"ORSY DU VOYAGE","naissance":"2024","date":"2026-06-25","hippodrome":"CAEN","lot":"-","reduction":"","reduction_date":"","discipline":"Attelé","urlPerfs":"https://www.letrot.com/stats/chevaux/ORSY-DU-VOYAGE/ZmZbYgIACgMH/courses"},{"nom":"OSAKA DU GUELIER","naissance":"2024","date":"2026-06-25","hippodrome":"CAEN","lot":"-","reduction":"","reduction_date":"","discipline":"Attelé","urlPerfs":"https://www.letrot.com/stats/chevaux/OSAKA-DU-GUELIER/ZmZbbAEFAgcT/courses"},{"nom":"OSAKA MESLOISE","naissance":"2024","date":"2026-06-25","hippodrome":"CAEN","lot":"-","reduction":"","reduction_date":"","discipline":"Attelé","urlPerfs":"https://www.letrot.com/stats/chevaux/OSAKA-MESLOISE/ZmZbYwYGAQcN/courses"},{"nom":"OSCAR DU BOCAGE","naissance":"2024","date":"2026-06-25","hippodrome":"CAEN","lot":"-","reduction":"","reduction_date":"","discipline":"Attelé","urlPerfs":"https://www.letrot.com/stats/chevaux/OSCAR-DU-BOCAGE/ZmZbbQAABQIB/courses"},{"nom":"OSCAR GLYCINES","naissance":"2024","date":"2026-06-25","hippodrome":"CAEN","lot":"-","reduction":"","reduction_date":"","discipline":"Attelé","urlPerfs":"https://www.letrot.com/stats/chevaux/OSCAR-GLYCINES/ZmZbYwcAAgoF/courses"},{"nom":"OSCARMEY","naissance":"2024","date":"2026-06-25","hippodrome":"CAEN","lot":"-","reduction":"","reduction_date":"","discipline":"Attelé","urlPerfs":"https://www.letrot.com/stats/chevaux/OSCARMEY/ZmZ9ZAcCAwoQ/courses"},{"nom":"OSMOSE DE BRY","naissance":"2024","date":"2026-06-25","hippodrome":"CAEN","lot":"-","reduction":"","reduction_date":"","discipline":"Attelé","urlPerfs":"https://www.letrot.com/stats/chevaux/OSMOSE-DE-BRY/ZmZbbQEAAwIN/courses"},{"nom":"OTAKARA DU PUITS","naissance":"2024","date":"2026-06-25","hippodrome":"CAEN","lot":"-","reduction":"","reduction_date":"","discipline":"Attelé","urlPerfs":"https://www.letrot.com/stats/chevaux/OTAKARA-DU-PUITS/ZmZbYgUFCwUN/courses"},{"nom":"OTAMA","naissance":"2024","date":"2026-06-25","hippodrome":"CAEN","lot":"-","reduction":"","reduction_date":"","discipline":"Attelé","urlPerfs":"https://www.letrot.com/stats/chevaux/OTAMA/ZmZbbAUGBgMY/courses"},{"nom":"OTHELLO D'AVE","naissance":"2024","date":"2026-06-25","hippodrome":"CAEN","lot":"-","reduction":"","reduction_date":"","discipline":"Attelé","urlPerfs":"https://www.letrot.com/stats/chevaux/OTHELLO-D%27AVE/ZmZbYwICBwce/courses"},{"nom":"OTHELLO DU VIVIER","naissance":"2024","date":"2026-06-25","hippodrome":"CAEN","lot":"-","reduction":"","reduction_date":"","discipline":"Attelé","urlPerfs":"https://www.letrot.com/stats/chevaux/OTHELLO-DU-VIVIER/ZmZbYwUEBAMW/courses"},{"nom":"OTTIMO AVIS","naissance":"2024","date":"2026-06-25","hippodrome":"CAEN","lot":"-","reduction":"","reduction_date":"","discipline":"Attelé","urlPerfs":"https://www.letrot.com/stats/chevaux/OTTIMO-AVIS/ZmZbYQAICgcE/courses"},{"nom":"OTTO SUPREME","naissance":"2024","date":"2026-06-25","hippodrome":"CAEN","lot":"-","reduction":"","reduction_date":"","discipline":"Attelé","urlPerfs":"https://www.letrot.com/stats/chevaux/OTTO-SUPREME/ZmZbYQUACgQD/courses"},{"nom":"OUBLIE JAMAIS","naissance":"2024","date":"2026-06-25","hippodrome":"CAEN","lot":"-","reduction":"1''1\"8","reduction_date":"19/06/2026","discipline":"Attelé","urlPerfs":"https://www.letrot.com/stats/chevaux/OUBLIE-JAMAIS/ZmZbbAEBAgcG/courses"},{"nom":"OUCKA DU QUENNE","naissance":"2024","date":"2026-06-25","hippodrome":"CAEN","lot":"-","reduction":"","reduction_date":"","discipline":"Attelé","urlPerfs":"https://www.letrot.com/stats/chevaux/OUCKA-DU-QUENNE/ZmZbYgYFCgMW/courses"},{"nom":"OUISTITI D'IDEE","naissance":"2024","date":"2026-06-25","hippodrome":"CAEN","lot":"-","reduction":"","reduction_date":"","discipline":"Attelé","urlPerfs":"https://www.letrot.com/stats/chevaux/OUISTITI-D%27IDEE/ZmZbbAoIAwIa/courses"},{"nom":"OULIPO","naissance":"2024","date":"2026-06-25","hippodrome":"CAEN","lot":"-","reduction":"","reduction_date":"","discipline":"Attelé","urlPerfs":"https://www.letrot.com/stats/chevaux/OULIPO/ZmZbbAoFBwEB/courses"},{"nom":"OUNARA","naissance":"2024","date":"2026-06-25","hippodrome":"CAEN","lot":"-","reduction":"","reduction_date":"","discipline":"Attelé","urlPerfs":"https://www.letrot.com/stats/chevaux/OUNARA/ZmZbYgQFBwIe/courses"},{"nom":"OURA D'AUBRIERE","naissance":"2024","date":"2026-06-25","hippodrome":"CAEN","lot":"-","reduction":"","reduction_date":"","discipline":"Attelé","urlPerfs":"https://www.letrot.com/stats/chevaux/OURA-D%27AUBRIERE/ZmZbbAEABAIa/courses"},{"nom":"OURAGAN DE BOISNEY","naissance":"2024","date":"2026-06-25","hippodrome":"CAEN","lot":"-","reduction":"","reduction_date":"","discipline":"Attelé","urlPerfs":"https://www.letrot.com/stats/chevaux/OURAGAN-DE-BOISNEY/ZmZbYwsEBgIN/courses"},{"nom":"OURAGANE JENILOU","naissance":"2024","date":"2026-06-25","hippodrome":"CAEN","lot":"-","reduction":"","reduction_date":"","discipline":"Attelé","urlPerfs":"https://www.letrot.com/stats/chevaux/OURAGANE-JENILOU/ZmZbYgoBAgYB/courses"},{"nom":"OURAK SOMOLLI","naissance":"2024","date":"2026-06-25","hippodrome":"CAEN","lot":"-","reduction":"","reduction_date":"","discipline":"Attelé","urlPerfs":"https://www.letrot.com/stats/chevaux/OURAK-SOMOLLI/ZmZbYgQBCwMW/courses"},{"nom":"OVER THE SKY","naissance":"2024","date":"2026-06-25","hippodrome":"CAEN","lot":"-","reduction":"","reduction_date":"","discipline":"Attelé","urlPerfs":"https://www.letrot.com/stats/chevaux/OVER-THE-SKY/ZmZbYwsFAQEO/courses"},{"nom":"OVER TO YOU","naissance":"2024","date":"2026-06-25","hippodrome":"CAEN","lot":"-","reduction":"","reduction_date":"","discipline":"Attelé","urlPerfs":"https://www.letrot.com/stats/chevaux/OVER-TO-YOU/ZmZbYwAFBgcB/courses"},{"nom":"OVERDOSE BILOU","naissance":"2024","date":"2026-06-25","hippodrome":"CAEN","lot":"-","reduction":"","reduction_date":"","discipline":"Attelé","urlPerfs":"https://www.letrot.com/stats/chevaux/OVERDOSE-BILOU/ZmZbbAoGBgsF/courses"},{"nom":"OVERSIZE DE LOCQ","naissance":"2024","date":"2026-06-25","hippodrome":"CAEN","lot":"-","reduction":"","reduction_date":"","discipline":"Attelé","urlPerfs":"https://www.letrot.com/stats/chevaux/OVERSIZE-DE-LOCQ/ZmZbbAAGBwsW/courses"},{"nom":"OVNI DE CAPONET","naissance":"2024","date":"2026-06-25","hippodrome":"CAEN","lot":"-","reduction":"","reduction_date":"","discipline":"Attelé","urlPerfs":"https://www.letrot.com/stats/chevaux/OVNI-DE-CAPONET/ZmZbbQUHBwcH/courses"},{"nom":"OXALIS DU RIB","naissance":"2024","date":"2026-06-25","hippodrome":"CAEN","lot":"-","reduction":"","reduction_date":"","discipline":"Attelé","urlPerfs":"https://www.letrot.com/stats/chevaux/OXALIS-DU-RIB/ZmZbYQoCBQEc/courses"},{"nom":"OXFORD DREAM","naissance":"2024","date":"2026-06-25","hippodrome":"CAEN","lot":"-","reduction":"","reduction_date":"","discipline":"Attelé","urlPerfs":"https://www.letrot.com/stats/chevaux/OXFORD-DREAM/ZmZbbAIBCwAS/courses"},{"nom":"OXIA JIEL","naissance":"2024","date":"2026-06-25","hippodrome":"CAEN","lot":"-","reduction":"","reduction_date":"","discipline":"Attelé","urlPerfs":"https://www.letrot.com/stats/chevaux/OXIA-JIEL/ZmZbYgQCAQUW/courses"},{"nom":"OXO MY HERO","naissance":"2024","date":"2026-06-25","hippodrome":"CAEN","lot":"-","reduction":"","reduction_date":"","discipline":"Attelé","urlPerfs":"https://www.letrot.com/stats/chevaux/OXO-MY-HERO/ZmZbbAMFAgsW/courses"}],"2026-06-26":[{"nom":"OBELIX QUICK","naissance":"2024","date":"2026-06-26","hippodrome":"FEURS","lot":"1","reduction":"","reduction_date":"","discipline":"Attelé","urlPerfs":"https://www.letrot.com/stats/chevaux/OBELIX-QUICK/ZmZbYgUFBQEO/courses"},{"nom":"ODESSA DE MONGOCHY","naissance":"2024","date":"2026-06-26","hippodrome":"FEURS","lot":"1","reduction":"","reduction_date":"","discipline":"Attelé","urlPerfs":"https://www.letrot.com/stats/chevaux/ODESSA-DE-MONGOCHY/ZmZbbQEDAgcR/courses"},{"nom":"OLAF DE SANA","naissance":"2024","date":"2026-06-26","hippodrome":"FEURS","lot":"1","reduction":"","reduction_date":"","discipline":"Attelé","urlPerfs":"https://www.letrot.com/stats/chevaux/OLAF-DE-SANA/ZmZbYwcJBwAE/courses"},{"nom":"OLOVE DES CHARRONS","naissance":"2024","date":"2026-06-26","hippodrome":"FEURS","lot":"1","reduction":"","reduction_date":"","discipline":"Attelé","urlPerfs":"https://www.letrot.com/stats/chevaux/OLOVE-DES-CHARRONS/ZmZbbAYEAwYG/courses"},{"nom":"ONLY LOVE","naissance":"2024","date":"2026-06-26","hippodrome":"FEURS","lot":"1","reduction":"","reduction_date":"","discipline":"Attelé","urlPerfs":"https://www.letrot.com/stats/chevaux/ONLY-LOVE/ZmZbYwMHAAoS/courses"},{"nom":"OPALINE DE LA LYRE","naissance":"2024","date":"2026-06-26","hippodrome":"FEURS","lot":"1","reduction":"","reduction_date":"","discipline":"Attelé","urlPerfs":"https://www.letrot.com/stats/chevaux/OPALINE-DE-LA-LYRE/ZmZbYgoGBAAa/courses"},{"nom":"OURA DE BERTRANGE","naissance":"2024","date":"2026-06-26","hippodrome":"FEURS","lot":"1","reduction":"","reduction_date":"","discipline":"Attelé","urlPerfs":"https://www.letrot.com/stats/chevaux/OURA-DE-BERTRANGE/ZmZbYQUJBgAF/courses"},{"nom":"OZAKA DU SERAN","naissance":"2024","date":"2026-06-26","hippodrome":"FEURS","lot":"1","reduction":"","reduction_date":"","discipline":"Attelé","urlPerfs":"https://www.letrot.com/stats/chevaux/OZAKA-DU-SERAN/ZmZbbQUCBAIQ/courses"},{"nom":"OLYMPIADE CITRUS","naissance":"2024","date":"2026-06-26","hippodrome":"FEURS","lot":"2","reduction":"","reduction_date":"","discipline":"Attelé","urlPerfs":"https://www.letrot.com/stats/chevaux/OLYMPIADE-CITRUS/ZmZbYwEBCwUY/courses"},{"nom":"OMER DE JOUX","naissance":"2024","date":"2026-06-26","hippodrome":"FEURS","lot":"2","reduction":"","reduction_date":"","discipline":"Attelé","urlPerfs":"https://www.letrot.com/stats/chevaux/OMER-DE-JOUX/ZmZbbAcDAQQE/courses"},{"nom":"ONESTO DU LOISIR","naissance":"2024","date":"2026-06-26","hippodrome":"FEURS","lot":"2","reduction":"","reduction_date":"","discipline":"Attelé","urlPerfs":"https://www.letrot.com/stats/chevaux/ONESTO-DU-LOISIR/ZmZbYgUGBwoR/courses"},{"nom":"ONLY YOU D'EMOTION","naissance":"2024","date":"2026-06-26","hippodrome":"FEURS","lot":"2","reduction":"","reduction_date":"","discipline":"Attelé","urlPerfs":"https://www.letrot.com/stats/chevaux/ONLY-YOU-D%27EMOTION/ZmZbbAAGAwoA/courses"},{"nom":"OPIUM KADESH","naissance":"2024","date":"2026-06-26","hippodrome":"FEURS","lot":"2","reduction":"","reduction_date":"","discipline":"Attelé","urlPerfs":"https://www.letrot.com/stats/chevaux/OPIUM-KADESH/ZmZbbAoFBwMM/courses"},{"nom":"OSHEN DES CHARRONS","naissance":"2024","date":"2026-06-26","hippodrome":"FEURS","lot":"2","reduction":"","reduction_date":"","discipline":"Attelé","urlPerfs":"https://www.letrot.com/stats/chevaux/OSHEN-DES-CHARRONS/ZmZbbQQFCwIT/courses"},{"nom":"OSMOSE DREAM","naissance":"2024","date":"2026-06-26","hippodrome":"FEURS","lot":"2","reduction":"","reduction_date":"","discipline":"Attelé","urlPerfs":"https://www.letrot.com/stats/chevaux/OSMOSE-DREAM/ZmZbbQcGAwIM/courses"},{"nom":"OTELLOMAN","naissance":"2024","date":"2026-06-26","hippodrome":"FEURS","lot":"2","reduction":"","reduction_date":"","discipline":"Attelé","urlPerfs":"https://www.letrot.com/stats/chevaux/OTELLOMAN/ZmZ9ZAcBBgoR/courses"},{"nom":"MAESTRIA DELDO","naissance":"2022","date":"2026-06-26","hippodrome":"FEURS","lot":"3","reduction":"","reduction_date":"","discipline":"Attelé","urlPerfs":"https://www.letrot.com/stats/chevaux/MAESTRIA-DELDO/ZmBbYwMFAgoc/courses"},{"nom":"MALICE DES DURIEZ","naissance":"2022","date":"2026-06-26","hippodrome":"FEURS","lot":"3","reduction":"","reduction_date":"","discipline":"Attelé","urlPerfs":"https://www.letrot.com/stats/chevaux/MALICE-DES-DURIEZ/ZmB9ZgoBAgIB/courses"},{"nom":"NABAB D'ORCO","naissance":"2023","date":"2026-06-26","hippodrome":"FEURS","lot":"3","reduction":"","reduction_date":"","discipline":"Attelé","urlPerfs":"https://www.letrot.com/stats/chevaux/NABAB-D%27ORCO/ZmF8YQQIBAMc/courses"},{"nom":"NAMASTE ESJI","naissance":"2023","date":"2026-06-26","hippodrome":"FEURS","lot":"3","reduction":"","reduction_date":"","discipline":"Attelé","urlPerfs":"https://www.letrot.com/stats/chevaux/NAMASTE-ESJI/ZmF8YgICBwYH/courses"},{"nom":"NEXANE BERRY","naissance":"2023","date":"2026-06-26","hippodrome":"FEURS","lot":"3","reduction":"","reduction_date":"","discipline":"Attelé","urlPerfs":"https://www.letrot.com/stats/chevaux/NEXANE-BERRY/ZmF8ZgcFCgQV/courses"},{"nom":"NICEGIRL DE DALINE","naissance":"2023","date":"2026-06-26","hippodrome":"FEURS","lot":"3","reduction":"","reduction_date":"","discipline":"Attelé","urlPerfs":"https://www.letrot.com/stats/chevaux/NICEGIRL-DE-DALINE/ZmF8ZwYDAwoe/courses"},{"nom":"NOBLESSE DU ROI","naissance":"2023","date":"2026-06-26","hippodrome":"FEURS","lot":"3","reduction":"","reduction_date":"","discipline":"Attelé","urlPerfs":"https://www.letrot.com/stats/chevaux/NOBLESSE-DU-ROI/ZmF8ZwECAwEZ/courses"},{"nom":"NUANCE ROMO","naissance":"2023","date":"2026-06-26","hippodrome":"FEURS","lot":"3","reduction":"","reduction_date":"","discipline":"Attelé","urlPerfs":"https://www.letrot.com/stats/chevaux/NUANCE-ROMO/ZmF8ZwECAAUM/courses"},{"nom":"OCEAN THREE","naissance":"2024","date":"2026-06-26","hippodrome":"FEURS","lot":"4","reduction":"","reduction_date":"","discipline":"Attelé","urlPerfs":"https://www.letrot.com/stats/chevaux/OCEAN-THREE/ZmZbbAcDAwcE/courses"},{"nom":"OEUVRE DIVINE","naissance":"2024","date":"2026-06-26","hippodrome":"FEURS","lot":"4","reduction":"","reduction_date":"","discipline":"Attelé","urlPerfs":"https://www.letrot.com/stats/chevaux/OEUVRE-DIVINE/ZmZbYgQBBQED/courses"},{"nom":"OH MON BATEAU","naissance":"2024","date":"2026-06-26","hippodrome":"FEURS","lot":"4","reduction":"","reduction_date":"","discipline":"Attelé","urlPerfs":"https://www.letrot.com/stats/chevaux/OH-MON-BATEAU/ZmZbYgsCBQQD/courses"},{"nom":"ONZIEME JOUR","naissance":"2024","date":"2026-06-26","hippodrome":"FEURS","lot":"4","reduction":"","reduction_date":"","discipline":"Attelé","urlPerfs":"https://www.letrot.com/stats/chevaux/ONZIEME-JOUR/ZmZbYgQIBQcc/courses"},{"nom":"OUALI ELGEO","naissance":"2024","date":"2026-06-26","hippodrome":"FEURS","lot":"4","reduction":"","reduction_date":"","discipline":"Attelé","urlPerfs":"https://www.letrot.com/stats/chevaux/OUALI-ELGEO/ZmZbbQACAAMc/courses"},{"nom":"OXANA DE MONGOCHY","naissance":"2024","date":"2026-06-26","hippodrome":"FEURS","lot":"4","reduction":"","reduction_date":"","discipline":"Attelé","urlPerfs":"https://www.letrot.com/stats/chevaux/OXANA-DE-MONGOCHY/ZmZbYgsDBwEE/courses"},{"nom":"NABU DE JOMAX","naissance":"2023","date":"2026-06-26","hippodrome":"FEURS","lot":"5","reduction":"","reduction_date":"","discipline":"Attelé","urlPerfs":"https://www.letrot.com/stats/chevaux/NABU-DE-JOMAX/ZmF8ZQABCwsQ/courses"},{"nom":"NAPOLINE DE BETAN","naissance":"2023","date":"2026-06-26","hippodrome":"FEURS","lot":"5","reduction":"","reduction_date":"","discipline":"Attelé","urlPerfs":"https://www.letrot.com/stats/chevaux/NAPOLINE-DE-BETAN/ZmF8ZgMGAwAB/courses"},{"nom":"NAYA DOUCETTE","naissance":"2023","date":"2026-06-26","hippodrome":"FEURS","lot":"5","reduction":"","reduction_date":"","discipline":"Attelé","urlPerfs":"https://www.letrot.com/stats/chevaux/NAYA-DOUCETTE/ZmF8ZQIIBAQV/courses"},{"nom":"NENA DES SOURCES","naissance":"2023","date":"2026-06-26","hippodrome":"FEURS","lot":"5","reduction":"","reduction_date":"","discipline":"Attelé","urlPerfs":"https://www.letrot.com/stats/chevaux/NENA-DES-SOURCES/ZmF8ZwYCCgMW/courses"},{"nom":"NEVER GO BACK","naissance":"2023","date":"2026-06-26","hippodrome":"FEURS","lot":"5","reduction":"","reduction_date":"","discipline":"Attelé","urlPerfs":"https://www.letrot.com/stats/chevaux/NEVER-GO-BACK/ZmF8ZgUBBwUB/courses"},{"nom":"NOBLESSE FILO","naissance":"2023","date":"2026-06-26","hippodrome":"FEURS","lot":"6","reduction":"","reduction_date":"","discipline":"Monté","urlPerfs":"https://www.letrot.com/stats/chevaux/NOBLESSE-FILO/ZmF8ZQsIBAsG/courses"},{"nom":"OREL SAM","naissance":"2024","date":"2026-06-26","hippodrome":"FEURS","lot":"7","reduction":"","reduction_date":"","discipline":"Attelé","urlPerfs":"https://www.letrot.com/stats/chevaux/OREL-SAM/ZmZbYgsDBgYM/courses"},{"nom":"MARQUISE DE BEE","naissance":"2022","date":"2026-06-26","hippodrome":"FEURS","lot":"-","reduction":"","reduction_date":"","discipline":"Monté","urlPerfs":"https://www.letrot.com/stats/chevaux/MARQUISE-DE-BEE/ZmBbYQYAAAMH/courses"},{"nom":"MILTON DE MOULIERE","naissance":"2022","date":"2026-06-26","hippodrome":"FEURS","lot":"-","reduction":"1''1\"7","reduction_date":"17/06/2026","discipline":"Monté","urlPerfs":"https://www.letrot.com/stats/chevaux/MILTON-DE-MOULIERE/ZmBbYgIGCgEW/courses"},{"nom":"MISS DES PRES","naissance":"2022","date":"2026-06-26","hippodrome":"FEURS","lot":"-","reduction":"","reduction_date":"","discipline":"Monté","urlPerfs":"https://www.letrot.com/stats/chevaux/MISS-DES-PRES/ZmBbbQoCAwQX/courses"},{"nom":"NAYA DES VALERINS","naissance":"2023","date":"2026-06-26","hippodrome":"FEURS","lot":"-","reduction":"","reduction_date":"","discipline":"Monté","urlPerfs":"https://www.letrot.com/stats/chevaux/NAYA-DES-VALERINS/ZmF8ZgMFAwMT/courses"},{"nom":"NEMO DE L'AUMANCE","naissance":"2023","date":"2026-06-26","hippodrome":"FEURS","lot":"-","reduction":"","reduction_date":"","discipline":"Monté","urlPerfs":"https://www.letrot.com/stats/chevaux/NEMO-DE-L%27AUMANCE/ZmF8ZgQDAgEN/courses"},{"nom":"NEPTUNE DU ROCH","naissance":"2023","date":"2026-06-26","hippodrome":"FEURS","lot":"-","reduction":"","reduction_date":"","discipline":"Monté","urlPerfs":"https://www.letrot.com/stats/chevaux/NEPTUNE-DU-ROCH/ZmF8YAQFBwsS/courses"},{"nom":"NEVER LOST","naissance":"2023","date":"2026-06-26","hippodrome":"FEURS","lot":"-","reduction":"","reduction_date":"","discipline":"Monté","urlPerfs":"https://www.letrot.com/stats/chevaux/NEVER-LOST/ZmF8YAcJBgcN/courses"},{"nom":"NEWTON FLEX","naissance":"2023","date":"2026-06-26","hippodrome":"FEURS","lot":"-","reduction":"","reduction_date":"","discipline":"Monté","urlPerfs":"https://www.letrot.com/stats/chevaux/NEWTON-FLEX/ZmF8bAABCgcT/courses"},{"nom":"NICKEL DE TERRAIL","naissance":"2023","date":"2026-06-26","hippodrome":"FEURS","lot":"-","reduction":"","reduction_date":"","discipline":"Monté","urlPerfs":"https://www.letrot.com/stats/chevaux/NICKEL-DE-TERRAIL/ZmF8ZQMHBAUN/courses"},{"nom":"NIKIE DE SANA","naissance":"2023","date":"2026-06-26","hippodrome":"FEURS","lot":"-","reduction":"","reduction_date":"","discipline":"Monté","urlPerfs":"https://www.letrot.com/stats/chevaux/NIKIE-DE-SANA/ZmF8ZgcEAAUV/courses"},{"nom":"NO MERCY","naissance":"2023","date":"2026-06-26","hippodrome":"FEURS","lot":"-","reduction":"","reduction_date":"","discipline":"Monté","urlPerfs":"https://www.letrot.com/stats/chevaux/NO-MERCY/ZmF8ZQcDBwEV/courses"},{"nom":"NORIA DES BORDES","naissance":"2023","date":"2026-06-26","hippodrome":"FEURS","lot":"-","reduction":"","reduction_date":"","discipline":"Monté","urlPerfs":"https://www.letrot.com/stats/chevaux/NORIA-DES-BORDES/ZmF8ZgsJBwsO/courses"},{"nom":"NORTHUG","naissance":"2023","date":"2026-06-26","hippodrome":"FEURS","lot":"-","reduction":"","reduction_date":"","discipline":"Monté","urlPerfs":"https://www.letrot.com/stats/chevaux/NORTHUG/ZmF8ZwoIAQoD/courses"},{"nom":"NOUBA DU MESNIL","naissance":"2023","date":"2026-06-26","hippodrome":"FEURS","lot":"-","reduction":"","reduction_date":"","discipline":"Monté","urlPerfs":"https://www.letrot.com/stats/chevaux/NOUBA-DU-MESNIL/ZmF8ZgAJCwAB/courses"},{"nom":"NOVA MAJOR","naissance":"2023","date":"2026-06-26","hippodrome":"FEURS","lot":"-","reduction":"","reduction_date":"","discipline":"Monté","urlPerfs":"https://www.letrot.com/stats/chevaux/NOVA-MAJOR/ZmF8ZQIICgMY/courses"},{"nom":"O'NARO","naissance":"2024","date":"2026-06-26","hippodrome":"FEURS","lot":"-","reduction":"","reduction_date":"","discipline":"Monté","urlPerfs":"https://www.letrot.com/stats/chevaux/O%27NARO/ZmZbYgcFAQUZ/courses"},{"nom":"O'PALERMO","naissance":"2024","date":"2026-06-26","hippodrome":"FEURS","lot":"-","reduction":"","reduction_date":"","discipline":"Monté","urlPerfs":"https://www.letrot.com/stats/chevaux/O%27PALERMO/ZmZbbAIABgUF/courses"},{"nom":"OBOFIX","naissance":"2024","date":"2026-06-26","hippodrome":"FEURS","lot":"-","reduction":"1''1\"9","reduction_date":"11/06/2026","discipline":"Monté","urlPerfs":"https://www.letrot.com/stats/chevaux/OBOFIX/ZmZbYgEHBAca/courses"},{"nom":"OH PRECIEUSE MAB","naissance":"2024","date":"2026-06-26","hippodrome":"FEURS","lot":"-","reduction":"1''1\"8","reduction_date":"22/06/2026","discipline":"Monté","urlPerfs":"https://www.letrot.com/stats/chevaux/OH-PRECIEUSE-MAB/ZmZbYwcEAAEG/courses"},{"nom":"OKELIA DOLL","naissance":"2024","date":"2026-06-26","hippodrome":"FEURS","lot":"-","reduction":"","reduction_date":"","discipline":"Monté","urlPerfs":"https://www.letrot.com/stats/chevaux/OKELIA-DOLL/ZmZbYQQGCwsA/courses"},{"nom":"ONE GOOD LUCK","naissance":"2024","date":"2026-06-26","hippodrome":"FEURS","lot":"-","reduction":"","reduction_date":"","discipline":"Monté","urlPerfs":"https://www.letrot.com/stats/chevaux/ONE-GOOD-LUCK/ZmZbYgsCBwEN/courses"},{"nom":"ONLY DE BERTRANGE","naissance":"2024","date":"2026-06-26","hippodrome":"FEURS","lot":"-","reduction":"","reduction_date":"","discipline":"Monté","urlPerfs":"https://www.letrot.com/stats/chevaux/ONLY-DE-BERTRANGE/ZmZbYQAJAQME/courses"},{"nom":"OREO MIO","naissance":"2024","date":"2026-06-26","hippodrome":"FEURS","lot":"-","reduction":"","reduction_date":"","discipline":"Monté","urlPerfs":"https://www.letrot.com/stats/chevaux/OREO-MIO/ZmZbbQAABQMD/courses"},{"nom":"OSAKA DE BERTRANGE","naissance":"2024","date":"2026-06-26","hippodrome":"FEURS","lot":"-","reduction":"1''2\"0","reduction_date":"11/06/2026","discipline":"Monté","urlPerfs":"https://www.letrot.com/stats/chevaux/OSAKA-DE-BERTRANGE/ZmZbYwUIAwEA/courses"},{"nom":"OSCAR DU GOUTIER","naissance":"2024","date":"2026-06-26","hippodrome":"FEURS","lot":"-","reduction":"","reduction_date":"","discipline":"Monté","urlPerfs":"https://www.letrot.com/stats/chevaux/OSCAR-DU-GOUTIER/ZmZbYgoEAgUH/courses"},{"nom":"OURA DELAPRADELLE","naissance":"2024","date":"2026-06-26","hippodrome":"FEURS","lot":"-","reduction":"","reduction_date":"","discipline":"Monté","urlPerfs":"https://www.letrot.com/stats/chevaux/OURA-DELAPRADELLE/ZmZbbQYEAwoH/courses"},{"nom":"OVERLORD BEZILLAT","naissance":"2024","date":"2026-06-26","hippodrome":"FEURS","lot":"-","reduction":"1''1\"9","reduction_date":"11/06/2026","discipline":"Monté","urlPerfs":"https://www.letrot.com/stats/chevaux/OVERLORD-BEZILLAT/ZmZbYQUCAwcc/courses"}]}